{"name": "Anic Mario", "sex": "M", "races": {"Basler Stadtlauf": {"latitude": 47.5595986, "longitude": 7.5885761, "race": "Basler Stadtlauf", "date": {"sam. 25.11.2006": {"year": 2006, "day": 25, "month": 11, "categories": {"C": {"distance": 2, "rank": 88, "pace": 260000000000, "time": 416.1}}, "weekday": "saturday", "livingplace": "Basel"}, "sam. 29.11.2003": {"year": 2003, "day": 29, "month": 11, "categories": {"A": {"distance": 1, "rank": 240, "pace": 304000000000, "time": 304.0}}, "weekday": "saturday", "livingplace": "Basel"}, "sam. 26.11.2005": {"year": 2005, "day": 26, "month": 11, "categories": {"C": {"distance": 2, "rank": 173, "pace": 285000000000, "time": 456.5}}, "weekday": "saturday", "livingplace": "Basel"}, "sam. 27.11.2004": {"year": 2004, "day": 27, "month": 11, "categories": {"A": {"distance": 1, "rank": 193, "pace": 285000000000, "time": 285.7}}, "weekday": "saturday", "livingplace": "Basel"}}, "location": "Basel"}}, "birth": 1994}