{"name": "Beney Jessy", "sex": "F", "races": {"Morat-Fribourg": {"latitude": 46.92922110000001, "longitude": 7.120184, "race": "Morat-Fribourg", "date": {"sam. 03.10.2015": {"year": 2015, "day": 3, "month": 10, "categories": {"17-W20": {"distance": 17, "rank": 621, "pace": 413000000000, "time": 7094.6}}, "weekday": "saturday", "livingplace": "Lens"}}, "location": "Murten"}, "SwissCityMarathon - Lucerne, Luzern": {"latitude": 47.05016819999999, "longitude": 8.3093072, "race": "SwissCityMarathon - Lucerne, Luzern", "date": {"dim. 25.10.2015": {"year": 2015, "day": 25, "month": 10, "categories": {"H-W30": {"distance": 21, "rank": 299, "pace": 383000000000, "time": 8096.0}}, "weekday": "sunday", "livingplace": "Lens"}}, "location": "Luzern"}, "Schweizer Frauenlauf Bern": {"latitude": 46.9479739, "longitude": 7.4474468, "race": "Schweizer Frauenlauf Bern", "date": {"dim. 14.06.2015": {"year": 2015, "day": 14, "month": 6, "categories": {"10-W30": {"distance": 10, "rank": 480, "pace": 411000000000, "time": 4113.7}}, "weekday": "sunday", "livingplace": "Lens"}}, "location": "Bern"}}, "birth": 1985}