{"name": "Berthoud Daniel", "sex": "M", "races": {"20km de Lausanne": {"latitude": 46.5196535, "longitude": 6.6322734, "race": "20km de Lausanne", "date": {"sam. 27.04.2013": {"year": 2013, "day": 27, "month": 4, "categories": {"10-H40": {"distance": 10, "rank": 444, "pace": 345000000000, "time": 3450.0}}, "weekday": "saturday", "livingplace": "Marsens"}, "sam. 25.04.2009": {"year": 2009, "day": 25, "month": 4, "categories": {"10-H30": {"distance": 10, "rank": 669, "pace": 349000000000, "time": 3495.3}}, "weekday": "saturday", "livingplace": "Marsens"}, "sam. 26.04.2014": {"year": 2014, "day": 26, "month": 4, "categories": {"10-H40": {"distance": 10, "rank": 415, "pace": 351000000000, "time": 3514.2}}, "weekday": "saturday", "livingplace": "Marsens"}, "sam. 22.04.2006": {"year": 2006, "day": 22, "month": 4, "categories": {"10/H30": {"distance": 10, "rank": 479, "pace": 366000000000, "time": 3663.2}}, "weekday": "saturday", "livingplace": "Marsens"}}, "location": "Lausanne"}, "Morat-Fribourg": {"latitude": 46.92922110000001, "longitude": 7.120184, "race": "Morat-Fribourg", "date": {"sam. 05.10.2013": {"year": 2013, "day": 5, "month": 10, "categories": {"17-M40": {"distance": 17, "rank": 801, "pace": 368000000000, "time": 6431.5}}, "weekday": "saturday", "livingplace": "Marsens"}, "sam. 01.10.2011": {"year": 2011, "day": 1, "month": 10, "categories": {"17-M40": {"distance": 17, "rank": 710, "pace": 383000000000, "time": 6585.6}}, "weekday": "saturday", "livingplace": "Marsens"}, "sam. 06.10.2012": {"year": 2012, "day": 6, "month": 10, "categories": {"17-M40": {"distance": 17, "rank": 705, "pace": 367000000000, "time": 6408.6}}, "weekday": "saturday", "livingplace": "Marsens"}, "sam. 04.10.2014": {"year": 2014, "day": 4, "month": 10, "categories": {"17-M40": {"distance": 17, "rank": 684, "pace": 370000000000, "time": 6358.9}}, "weekday": "saturday", "livingplace": "Marsens"}}, "location": "Murten"}, "Kerzerslauf": {"latitude": 46.97488999999999, "longitude": 7.1954365, "race": "Kerzerslauf", "date": {"sam. 15.03.2014": {"year": 2014, "day": 15, "month": 3, "categories": {"15-M40": {"distance": 15, "rank": 506, "pace": 368000000000, "time": 5525.5}}, "weekday": "saturday", "livingplace": "Marsens"}}, "location": "Kerzers"}}, "birth": 1971}