{"name": "Bohren Matthias", "sex": "M", "races": {"Eiger Ultra Trail, Grindelwald": {"latitude": 46.624164, "longitude": 8.0413962, "race": "Eiger Ultra Trail, Grindelwald", "date": {"sam. 18.07.2015": {"year": 2015, "day": 18, "month": 7, "categories": {"K-2M": {"distance": 0, "rank": 8, "pace": 459000000000, "time": 160.8}}, "weekday": "saturday", "livingplace": "Grindelwald"}, "sam. 19.07.2014": {"year": 2014, "day": 19, "month": 7, "categories": {"K-2M": {"distance": 0, "rank": 6, "pace": 237000000000, "time": 83.0}}, "weekday": "saturday", "livingplace": "Grindelwald"}}, "location": "Grindelwald"}}, "birth": 2006}