{"name": "Bortesi Paola", "sex": "F", "races": {"Maratona Ticino, Tenero": {"latitude": NaN, "longitude": NaN, "race": "Maratona Ticino, Tenero", "date": {"dim. 14.11.2010": {"year": 2010, "day": 14, "month": 11, "categories": {"H-W45": {"distance": 21, "rank": 56, "pace": 357000000000, "time": 7533.8}}, "weekday": "sunday", "livingplace": "Saronno "}, "dim. 13.11.2011": {"year": 2011, "day": 13, "month": 11, "categories": {"H-W45": {"distance": 21, "rank": 72, "pace": 358000000000, "time": 7555.8}}, "weekday": "sunday", "livingplace": "Saronno "}}, "location": "Tenero"}}, "birth": 1965}