{"name": "Bridet J\u00e9r\u00f4me", "sex": "M", "races": {"Course Titz\u00e9 de no\u00ebl Sion": {"latitude": 46.2331221, "longitude": 7.360625999999999, "race": "Course Titz\u00e9 de no\u00ebl Sion", "date": {"sam. 14.12.2013": {"year": 2013, "day": 14, "month": 12, "categories": {"K-CMA": {"distance": 4, "rank": 18, "pace": 225000000000, "time": 901.6}}, "weekday": "saturday", "livingplace": "Sion"}, "sam. 10.12.2005": {"year": 2005, "day": 10, "month": 12, "categories": {"EMC": {"distance": 1, "rank": 21, "pace": 288000000000, "time": 303.1}}, "weekday": "saturday", "livingplace": "Sion"}, "sam. 08.12.2007": {"year": 2007, "day": 8, "month": 12, "categories": {"EMB": {"distance": 1, "rank": 21, "pace": 238000000000, "time": 238.3}}, "weekday": "saturday", "livingplace": "Sion"}, "sam. 13.12.2003": {"year": 2003, "day": 13, "month": 12, "categories": {"EMC": {"distance": 1, "rank": 90, "pace": 337000000000, "time": 354.1}}, "weekday": "saturday", "livingplace": "Sion"}, "sam. 09.12.2006": {"year": 2006, "day": 9, "month": 12, "categories": {"EMB": {"distance": 1, "rank": 38, "pace": 257000000000, "time": 282.8}}, "weekday": "saturday", "livingplace": "Sion"}}, "location": "Sion"}}, "birth": 1997}