{"name": "Corneil Dane", "sex": "M", "races": {"Lucerne Marathon, Luzern": {"latitude": 47.05016819999999, "longitude": 8.3093072, "race": "Lucerne Marathon, Luzern", "date": {"dim. 30.10.2011": {"year": 2011, "day": 30, "month": 10, "categories": {"H-M20": {"distance": 21, "rank": 559, "pace": 345000000000, "time": 7285.5}}, "weekday": "sunday", "livingplace": "Zurich"}}, "location": "Luzern"}, "Lausanne Marathon": {"latitude": 46.5196535, "longitude": 6.6322734, "race": "Lausanne Marathon", "date": {"dim. 27.10.2013": {"year": 2013, "day": 27, "month": 10, "categories": {"21-H1": {"distance": 21, "rank": 450, "pace": 332000000000, "time": 7014.8}}, "weekday": "sunday", "livingplace": "St Sulpice"}}, "location": "Lausanne"}, "20km de Lausanne": {"latitude": 46.5196535, "longitude": 6.6322734, "race": "20km de Lausanne", "date": {"sam. 27.04.2013": {"year": 2013, "day": 27, "month": 4, "categories": {"10-H20": {"distance": 10, "rank": 597, "pace": 318000000000, "time": 3188.0}}, "weekday": "saturday", "livingplace": "EP   Sciences de la Vie"}, "sam. 26.04.2014": {"year": 2014, "day": 26, "month": 4, "categories": {"10-H20": {"distance": 10, "rank": 738, "pace": 341000000000, "time": 3412.0}}, "weekday": "saturday", "livingplace": "Epfl Sv 6"}}, "location": "Lausanne"}}, "birth": 1986}