{"name": "Duclocher Jerome", "sex": "M", "races": {"Sierre-Zinal, Sierre": {"latitude": 46.29413110000001, "longitude": 7.533536199999999, "race": "Sierre-Zinal, Sierre", "date": {"dim. 10.08.2014": {"year": 2014, "day": 10, "month": 8, "categories": {"ElitesHo": {"distance": 31, "rank": 411, "pace": 527000000000, "time": 16364.1}}, "weekday": "sunday", "livingplace": "Miribel"}, "dim. 12.08.2012": {"year": 2012, "day": 12, "month": 8, "categories": {"Elites": {"distance": 31, "rank": 343, "pace": 551000000000, "time": 17101.4}}, "weekday": "sunday", "livingplace": "Miribel"}, "dim. 11.08.2013": {"year": 2013, "day": 11, "month": 8, "categories": {"Elites": {"distance": 31, "rank": 341, "pace": 540000000000, "time": 16746.3}}, "weekday": "sunday", "livingplace": "Miribel"}}, "location": "Sierre"}}, "birth": 1975}