{"name": "Dumoulin Yolande", "sex": "F", "races": {"Morat-Fribourg": {"latitude": 46.92922110000001, "longitude": 7.120184, "race": "Morat-Fribourg", "date": {"sam. 03.10.2009": {"year": 2009, "day": 3, "month": 10, "categories": {"C-W45": {"distance": 17, "rank": 165, "pace": 380000000000, "time": 6525.5}}, "weekday": "saturday", "livingplace": "Saviese"}, "sam. 04.10.2008": {"year": 2008, "day": 4, "month": 10, "categories": {"C-W45": {"distance": 17, "rank": 198, "pace": 383000000000, "time": 6587.2}}, "weekday": "saturday", "livingplace": "Saviese"}, "sam. 06.10.2012": {"year": 2012, "day": 6, "month": 10, "categories": {"17-W50": {"distance": 17, "rank": 103, "pace": 383000000000, "time": 6694.3}}, "weekday": "saturday", "livingplace": "Saviese"}, "sam. 04.10.2014": {"year": 2014, "day": 4, "month": 10, "categories": {"17-W50": {"distance": 17, "rank": 128, "pace": 396000000000, "time": 6811.2}}, "weekday": "saturday", "livingplace": "Saviese"}}, "location": "Murten"}, "Corrida Bulloise, Bulle": {"latitude": 46.6154512, "longitude": 7.057726799999999, "race": "Corrida Bulloise, Bulle", "date": {"sam. 17.11.2012": {"year": 2012, "day": 17, "month": 11, "categories": {"F50": {"distance": 6, "rank": 43, "pace": 340000000000, "time": 2094.9}}, "weekday": "saturday", "livingplace": "Saviese"}}, "location": "Bulle"}}, "birth": 1960}