{"name": "Fl\u00fcgel Anke", "sex": "F", "races": {"Augusta Raurica Lauf, Augst BL": {"latitude": NaN, "longitude": NaN, "race": "Augusta Raurica Lauf, Augst BL", "date": {"dim. 13.11.2011": {"year": 2011, "day": 13, "month": 11, "categories": {"12-F40": {"distance": 12, "rank": 32, "pace": 407000000000, "time": 4888.4}}, "weekday": "sunday", "livingplace": "Munchenstein"}}, "location": "Augst BL"}, "Schweizer Frauenlauf Bern": {"latitude": 46.9479739, "longitude": 7.4474468, "race": "Schweizer Frauenlauf Bern", "date": {"dim. 10.06.2012": {"year": 2012, "day": 10, "month": 6, "categories": {"10-W45": {"distance": 10, "rank": 465, "pace": 383000000000, "time": 3836.2}}, "weekday": "sunday", "livingplace": "Munchenstein"}, "dim. 14.06.2009": {"year": 2009, "day": 14, "month": 6, "categories": {"10-W45": {"distance": 10, "rank": 420, "pace": 399000000000, "time": 3995.9}}, "weekday": "sunday", "livingplace": "Munchenstein"}, "dim. 19.06.2011": {"year": 2011, "day": 19, "month": 6, "categories": {"10-W45": {"distance": 10, "rank": 484, "pace": 383000000000, "time": 3830.0}}, "weekday": "sunday", "livingplace": "Munchenstein"}, "dim. 10.06.2007": {"year": 2007, "day": 10, "month": 6, "categories": {"10/W40": {"distance": 10, "rank": 496, "pace": 379000000000, "time": 3791.5}}, "weekday": "sunday", "livingplace": "Munchenstein"}, "dim. 11.06.2006": {"year": 2006, "day": 11, "month": 6, "categories": {"10-W40": {"distance": 10, "rank": 287, "pace": 342000000000, "time": 3423.5}}, "weekday": "sunday", "livingplace": "Munchenstein"}, "dim. 09.06.2013": {"year": 2013, "day": 9, "month": 6, "categories": {"10-W50": {"distance": 10, "rank": 332, "pace": 411000000000, "time": 4118.9}}, "weekday": "sunday", "livingplace": "Munchenstein"}}, "location": "Bern"}, "Gempenlauf, Dornach": {"latitude": 47.4790491, "longitude": 7.6170412, "race": "Gempenlauf, Dornach", "date": {"mer. 03.06.2009": {"year": 2009, "day": 3, "month": 6, "categories": {"F45": {"distance": 8, "rank": 36, "pace": 463000000000, "time": 3612.0}}, "weekday": "wednesday", "livingplace": "Lsvb"}, "mer. 08.06.2011": {"year": 2011, "day": 8, "month": 6, "categories": {"F45": {"distance": 8, "rank": 29, "pace": 473000000000, "time": 3694.8}}, "weekday": "wednesday", "livingplace": "Munchenstein"}}, "location": "Dornach"}, "Int Greifenseelauf, Uster": {"latitude": 47.3482747, "longitude": 8.717873899999999, "race": "Int Greifenseelauf, Uster", "date": {"sam. 22.09.2007": {"year": 2007, "day": 22, "month": 9, "categories": {"M/W40": {"distance": 10, "rank": 103, "pace": 369000000000, "time": 3698.5}}, "weekday": "saturday", "livingplace": "Munchenstein"}, "sam. 17.09.2005": {"year": 2005, "day": 17, "month": 9, "categories": {"H/W40": {"distance": 21, "rank": 354, "pace": 351000000000, "time": 7418.4}}, "weekday": "saturday", "livingplace": "Munchenstein"}}, "location": "Uster"}, "Hallwilerseelauf, Beinwil am See": {"latitude": NaN, "longitude": NaN, "race": "Hallwilerseelauf, Beinwil am See", "date": {"sam. 15.10.2005": {"year": 2005, "day": 15, "month": 10, "categories": {"F40": {"distance": 21, "rank": 203, "pace": 358000000000, "time": 7571.7}}, "weekday": "saturday", "livingplace": "Munchenstein"}}, "location": "Beinwil am See"}, "Kerzerslauf": {"latitude": 46.97488999999999, "longitude": 7.1954365, "race": "Kerzerslauf", "date": {"sam. 18.03.2006": {"year": 2006, "day": 18, "month": 3, "categories": {"F40": {"distance": 15, "rank": 162, "pace": 345000000000, "time": 5178.9}}, "weekday": "saturday", "livingplace": "Munchenstein"}, "sam. 19.03.2005": {"year": 2005, "day": 19, "month": 3, "categories": {"F40": {"distance": 15, "rank": 178, "pace": 386000000000, "time": 5796.5}}, "weekday": "saturday", "livingplace": "Munchenstein"}, "sam. 17.03.2007": {"year": 2007, "day": 17, "month": 3, "categories": {"F40": {"distance": 15, "rank": 229, "pace": 371000000000, "time": 5577.0}}, "weekday": "saturday", "livingplace": "Munchenstein"}}, "location": "Kerzers"}, "GP Fricktal, Eiken": {"latitude": NaN, "longitude": NaN, "race": "GP Fricktal, Eiken", "date": {"sam. 11.04.2009": {"year": 2009, "day": 11, "month": 4, "categories": {"F40": {"distance": 16, "rank": 36, "pace": 408000000000, "time": 6572.9}}, "weekday": "saturday", "livingplace": "Munchenstein"}}, "location": "Eiken"}}, "birth": 1963}