{"name": "Gr\u00fcter Lea", "sex": "F", "races": {"Fl\u00e4ckelauf Berom\u00fcnster": {"latitude": NaN, "longitude": NaN, "race": "Fl\u00e4ckelauf Berom\u00fcnster", "date": {"sam. 15.05.2010": {"year": 2010, "day": 15, "month": 5, "categories": {"SchC-F": {"distance": 2, "rank": 23, "pace": 292000000000, "time": 470.6}}, "weekday": "saturday", "livingplace": "St. Urban"}, "sam. 16.05.2009": {"year": 2009, "day": 16, "month": 5, "categories": {"SchC-F": {"distance": 2, "rank": 29, "pace": 295000000000, "time": 475.9}}, "weekday": "saturday", "livingplace": "St. Urban"}, "sam. 17.05.2008": {"year": 2008, "day": 17, "month": 5, "categories": {"PiccoloF": {"distance": 1, "rank": 5, "pace": 276000000000, "time": 182.4}}, "weekday": "saturday", "livingplace": "St. Urban"}}, "location": "Berom\u00fcnster"}, "Luzerner Stadtlauf": {"latitude": 47.05016819999999, "longitude": 8.3093072, "race": "Luzerner Stadtlauf", "date": {"sam. 24.04.2010": {"year": 2010, "day": 24, "month": 4, "categories": {"K-7": {"distance": 2, "rank": 79, "pace": 281000000000, "time": 424.6}}, "weekday": "saturday", "livingplace": "Jugend St. Urban"}, "sam. 25.04.2009": {"year": 2009, "day": 25, "month": 4, "categories": {"K-7": {"distance": 2, "rank": 63, "pace": 278000000000, "time": 421.2}}, "weekday": "saturday", "livingplace": "Jugi St.Urban"}, "sam. 28.04.2007": {"year": 2007, "day": 28, "month": 4, "categories": {"K/7": {"distance": 2, "rank": 295, "pace": 339000000000, "time": 512.2}}, "weekday": "saturday", "livingplace": "St. Urban"}, "sam. 07.05.2011": {"year": 2011, "day": 7, "month": 5, "categories": {"K-7": {"distance": 2, "rank": 34, "pace": 265000000000, "time": 401.6}}, "weekday": "saturday", "livingplace": "Turnverein Jugend St. Urb"}, "sam. 26.04.2008": {"year": 2008, "day": 26, "month": 4, "categories": {"K/7": {"distance": 2, "rank": 198, "pace": 317000000000, "time": 478.7}}, "weekday": "saturday", "livingplace": "Jugend St. Urban"}}, "location": "Luzern"}}, "birth": 2001}