{"name": "Isenring Martin", "sex": "M", "races": {"Frauenfelder": {"latitude": NaN, "longitude": NaN, "race": "Frauenfelder", "date": {"dim. 18.11.2007": {"year": 2007, "day": 18, "month": 11, "categories": {"M30": {"distance": 42, "rank": 13, "pace": 333000000000, "time": 14087.8}}, "weekday": "sunday", "livingplace": "Schwyz 1"}}, "location": "Frauenfeld"}, "Int Greifenseelauf, Uster": {"latitude": 47.3482747, "longitude": 8.717873899999999, "race": "Int Greifenseelauf, Uster", "date": {"sam. 19.09.2009": {"year": 2009, "day": 19, "month": 9, "categories": {"H-M35": {"distance": 21, "rank": 436, "pace": 309000000000, "time": 6521.4}}, "weekday": "saturday", "livingplace": "Oberengstringen"}, "sam. 20.09.2008": {"year": 2008, "day": 20, "month": 9, "categories": {"H-M35": {"distance": 21, "rank": 284, "pace": 287000000000, "time": 6057.4}}, "weekday": "saturday", "livingplace": "Oberengstringen"}}, "location": "Uster"}, "Jungfrau-Marathon, Interlaken": {"latitude": NaN, "longitude": NaN, "race": "Jungfrau-Marathon, Interlaken", "date": {"sam. 09.09.2006": {"year": 2006, "day": 9, "month": 9, "categories": {"M20": {"distance": 42, "rank": 402, "pace": 413000000000, "time": 17455.3}}, "weekday": "saturday", "livingplace": "Oberengstringen"}, "sam. 08.09.2007": {"year": 2007, "day": 8, "month": 9, "categories": {"M20": {"distance": 42, "rank": 459, "pace": 413000000000, "time": 17437.7}}, "weekday": "saturday", "livingplace": "Oberengstringen"}, "sam. 06.09.2008": {"year": 2008, "day": 6, "month": 9, "categories": {"M20": {"distance": 42, "rank": 516, "pace": 440000000000, "time": 18600.1}}, "weekday": "saturday", "livingplace": "Oberengstringen"}, "sam. 08.09.2012": {"year": 2012, "day": 8, "month": 9, "categories": {"SO-M20": {"distance": 42, "rank": 740, "pace": 455000000000, "time": 19201.8}}, "weekday": "saturday", "livingplace": "Oberengstringen"}}, "location": "Interlaken"}, "ASICS Bremgarter Reusslauf": {"latitude": 47.34917739999999, "longitude": 8.3397905, "race": "ASICS Bremgarter Reusslauf", "date": {"sam. 23.02.2013": {"year": 2013, "day": 23, "month": 2, "categories": {"11-M40": {"distance": 11, "rank": 199, "pace": 264000000000, "time": 2906.7}}, "weekday": "saturday", "livingplace": "Post"}, "sam. 25.02.2006": {"year": 2006, "day": 25, "month": 2, "categories": {"M30": {"distance": 11, "rank": 195, "pace": 262000000000, "time": 2758.4}}, "weekday": "saturday", "livingplace": "Oberengstringen"}, "sam. 27.02.2010": {"year": 2010, "day": 27, "month": 2, "categories": {"M30": {"distance": 11, "rank": 190, "pace": 261000000000, "time": 2879.8}}, "weekday": "saturday", "livingplace": "Post"}, "sam. 26.02.2011": {"year": 2011, "day": 26, "month": 2, "categories": {"M30": {"distance": 11, "rank": 238, "pace": 271000000000, "time": 2984.3}}, "weekday": "saturday", "livingplace": "Post"}, "sam. 23.02.2008": {"year": 2008, "day": 23, "month": 2, "categories": {"M30": {"distance": 11, "rank": 181, "pace": 260000000000, "time": 2867.4}}, "weekday": "saturday", "livingplace": "Die Post"}, "sam. 25.02.2012": {"year": 2012, "day": 25, "month": 2, "categories": {"M30": {"distance": 11, "rank": 170, "pace": 257000000000, "time": 2830.9}}, "weekday": "saturday", "livingplace": "Post"}, "sam. 28.02.2015": {"year": 2015, "day": 28, "month": 2, "categories": {"11-M40": {"distance": 11, "rank": 291, "pace": 277000000000, "time": 3047.2}}, "weekday": "saturday", "livingplace": "Oberengstringen"}, "sam. 22.02.2014": {"year": 2014, "day": 22, "month": 2, "categories": {"11-M40": {"distance": 11, "rank": 268, "pace": 274000000000, "time": 3019.3}}, "weekday": "saturday", "livingplace": "Oberengstringen"}}, "location": "Bremgarten AG"}, "Z\u00fcrich Marathon, Teamrun und Cityrun": {"latitude": 47.3768866, "longitude": 8.541694, "race": "Z\u00fcrich Marathon, Teamrun und Cityrun", "date": {"dim. 06.04.2014": {"year": 2014, "day": 6, "month": 4, "categories": {"10-M40": {"distance": 10, "rank": 65, "pace": 260000000000, "time": 2557.1}}, "weekday": "sunday", "livingplace": "Oberengstringen"}, "dim. 09.04.2006": {"year": 2006, "day": 9, "month": 4, "categories": {"M30": {"distance": 42, "rank": 388, "pace": 285000000000, "time": 12045.2}}, "weekday": "sunday", "livingplace": "Oberengstringen"}, "dim. 01.04.2007": {"year": 2007, "day": 1, "month": 4, "categories": {"M30": {"distance": 42, "rank": 367, "pace": 284000000000, "time": 12004.2}}, "weekday": "sunday", "livingplace": "Oberengstringen"}, "dim. 19.04.2015": {"year": 2015, "day": 19, "month": 4, "categories": {"10-M40": {"distance": 10, "rank": 54, "pace": 261000000000, "time": 2566.4}}, "weekday": "sunday", "livingplace": "Oberengstringen"}, "dim. 26.04.2009": {"year": 2009, "day": 26, "month": 4, "categories": {"M30": {"distance": 42, "rank": 428, "pace": 306000000000, "time": 12943.6}}, "weekday": "sunday", "livingplace": "Oberengstringen"}, "dim. 22.04.2012": {"year": 2012, "day": 22, "month": 4, "categories": {"42-M30": {"distance": 42, "rank": 243, "pace": 306000000000, "time": 12912.4}}, "weekday": "sunday", "livingplace": "Oberengstringen"}, "dim. 17.04.2011": {"year": 2011, "day": 17, "month": 4, "categories": {"42-M30": {"distance": 42, "rank": 330, "pace": 311000000000, "time": 13147.5}}, "weekday": "sunday", "livingplace": "Oberengstringen"}, "dim. 20.04.2008": {"year": 2008, "day": 20, "month": 4, "categories": {"M30": {"distance": 42, "rank": 590, "pace": 313000000000, "time": 13246.7}}, "weekday": "sunday", "livingplace": "Oberengstringen"}}, "location": "Z\u00fcrich"}, "Hallwilerseelauf, Beinwil am See": {"latitude": NaN, "longitude": NaN, "race": "Hallwilerseelauf, Beinwil am See", "date": {"sam. 11.10.2014": {"year": 2014, "day": 11, "month": 10, "categories": {"21-M40": {"distance": 21, "rank": 328, "pace": 295000000000, "time": 6243.6}}, "weekday": "saturday", "livingplace": "Oberengstringen"}, "sam. 15.10.2011": {"year": 2011, "day": 15, "month": 10, "categories": {"21-M30": {"distance": 21, "rank": 298, "pace": 283000000000, "time": 5984.4}}, "weekday": "saturday", "livingplace": "Oberengstringen"}, "sam. 10.10.2015": {"year": 2015, "day": 10, "month": 10, "categories": {"21-M40": {"distance": 21, "rank": 367, "pace": 300000000000, "time": 6347.5}}, "weekday": "saturday", "livingplace": "Oberengstringen"}, "sam. 12.10.2013": {"year": 2013, "day": 12, "month": 10, "categories": {"21-M40": {"distance": 21, "rank": 346, "pace": 288000000000, "time": 6091.2}}, "weekday": "saturday", "livingplace": "Oberengstringen"}, "sam. 16.10.2010": {"year": 2010, "day": 16, "month": 10, "categories": {"21-M30": {"distance": 21, "rank": 271, "pace": 282000000000, "time": 5963.5}}, "weekday": "saturday", "livingplace": "Oberengstringen"}, "sam. 13.10.2012": {"year": 2012, "day": 13, "month": 10, "categories": {"21-M30": {"distance": 21, "rank": 247, "pace": 287000000000, "time": 6064.3}}, "weekday": "saturday", "livingplace": "Oberengstringen"}, "sam. 10.10.2009": {"year": 2009, "day": 10, "month": 10, "categories": {"21-M30": {"distance": 21, "rank": 229, "pace": 281000000000, "time": 5935.2}}, "weekday": "saturday", "livingplace": "Oberengstringen"}}, "location": "Beinwil am See"}, "Winterthur Marathon": {"latitude": 39.8088766, "longitude": -75.6037351, "race": "Winterthur Marathon", "date": {"dim. 16.05.2010": {"year": 2010, "day": 16, "month": 5, "categories": {"HM30": {"distance": 21, "rank": 89, "pace": 286000000000, "time": 6041.5}}, "weekday": "sunday", "livingplace": "Oberengstringen"}, "dim. 20.05.2007": {"year": 2007, "day": 20, "month": 5, "categories": {"MMAktiv": {"distance": 42, "rank": 23, "pace": 303000000000, "time": 12770.7}}, "weekday": "sunday", "livingplace": "Oberengstringen"}, "dim. 29.05.2011": {"year": 2011, "day": 29, "month": 5, "categories": {"H-M30": {"distance": 21, "rank": 115, "pace": 293000000000, "time": 6171.0}}, "weekday": "sunday", "livingplace": "Oberengstringen"}, "dim. 24.05.2009": {"year": 2009, "day": 24, "month": 5, "categories": {"HM30": {"distance": 21, "rank": 151, "pace": 318000000000, "time": 6717.4}}, "weekday": "sunday", "livingplace": "Oberengstringen"}, "dim. 18.05.2008": {"year": 2008, "day": 18, "month": 5, "categories": {"MM35": {"distance": 42, "rank": 14, "pace": 290000000000, "time": 12256.4}}, "weekday": "sunday", "livingplace": "Oberengstringen"}}, "location": "Winterthur"}, "Bieler Lauftage, Biel Bienne": {"latitude": 47.1367785, "longitude": 7.2467909, "race": "Bieler Lauftage, Biel Bienne", "date": {"ven. 13.06.2008": {"year": 2008, "day": 13, "month": 6, "categories": {"100/M35": {"distance": 100, "rank": 148, "pace": 443000000000, "time": 44336.4}}, "weekday": "friday", "livingplace": "Oberengstringen"}, "ven. 12.06.2009": {"year": 2009, "day": 12, "month": 6, "categories": {"100/M35": {"distance": 100, "rank": 57, "pace": 438000000000, "time": 43837.7}}, "weekday": "friday", "livingplace": "Oberengstringen"}}, "location": "Biel/Bienne"}, "Z\u00fcrcher Silvesterlauf, Z\u00fcrich": {"latitude": 47.3768866, "longitude": 8.541694, "race": "Z\u00fcrcher Silvesterlauf, Z\u00fcrich", "date": {"dim. 14.12.2008": {"year": 2008, "day": 14, "month": 12, "categories": {"MenAK1-8": {"distance": 9, "rank": 259, "pace": 259000000000, "time": 2230.2}}, "weekday": "sunday", "livingplace": "Oberengstringen"}, "dim. 15.12.2013": {"year": 2013, "day": 15, "month": 12, "categories": {"10-M40": {"distance": 10, "rank": 324, "pace": 264000000000, "time": 2646.2}}, "weekday": "sunday", "livingplace": "Oberengstringen"}, "dim. 16.12.2012": {"year": 2012, "day": 16, "month": 12, "categories": {"8-MM30": {"distance": 9, "rank": 288, "pace": 263000000000, "time": 2267.6}}, "weekday": "sunday", "livingplace": "Oberengstringen"}, "dim. 12.12.2010": {"year": 2010, "day": 12, "month": 12, "categories": {"8-MenAK1": {"distance": 9, "rank": 295, "pace": 264000000000, "time": 2275.3}}, "weekday": "sunday", "livingplace": "Oberengstringen"}, "dim. 16.12.2007": {"year": 2007, "day": 16, "month": 12, "categories": {"MenAK1-8": {"distance": 9, "rank": 261, "pace": 252000000000, "time": 2167.3}}, "weekday": "sunday", "livingplace": "Oberengstringen"}, "dim. 14.12.2014": {"year": 2014, "day": 14, "month": 12, "categories": {"10-M40": {"distance": 10, "rank": 380, "pace": 273000000000, "time": 2736.7}}, "weekday": "sunday", "livingplace": "Oberengstringen"}, "dim. 10.12.2006": {"year": 2006, "day": 10, "month": 12, "categories": {"MenAK1-8": {"distance": 9, "rank": 412, "pace": 257000000000, "time": 2217.9}}, "weekday": "sunday", "livingplace": "Oberengstringen"}, "dim. 13.12.2009": {"year": 2009, "day": 13, "month": 12, "categories": {"8-MenAK1": {"distance": 9, "rank": 248, "pace": 256000000000, "time": 2208.1}}, "weekday": "sunday", "livingplace": "Oberengstringen"}}, "location": "Z\u00fcrich"}}, "birth": 1973}