{"name": "Jouve Guillaume", "sex": "M", "races": {"Lausanne Marathon": {"latitude": 46.5196535, "longitude": 6.6322734, "race": "Lausanne Marathon", "date": {"dim. 28.10.2012": {"year": 2012, "day": 28, "month": 10, "categories": {"42-H3": {"distance": 42, "rank": 222, "pace": 333000000000, "time": 14079.4}}, "weekday": "sunday", "livingplace": "St Victor la Coste"}}, "location": "Lausanne"}, "20km de Lausanne": {"latitude": 46.5196535, "longitude": 6.6322734, "race": "20km de Lausanne", "date": {"sam. 22.04.2006": {"year": 2006, "day": 22, "month": 4, "categories": {"20/H40": {"distance": 20, "rank": 161, "pace": 301000000000, "time": 6025.9}}, "weekday": "saturday", "livingplace": "Saint Victor la Coste"}}, "location": "Lausanne"}}, "birth": 1966}