{"name": "Kathriner Noldi", "sex": "M", "races": {"Badener Limmat-Lauf, Baden": {"latitude": 48.5699281, "longitude": 8.5303972, "race": "Badener Limmat-Lauf, Baden", "date": {"sam. 28.03.2015": {"year": 2015, "day": 28, "month": 3, "categories": {"M40": {"distance": 13, "rank": 153, "pace": 323000000000, "time": 4266.0}}, "weekday": "saturday", "livingplace": "Sarnen"}}, "location": "Baden"}, "Kerzerslauf": {"latitude": 46.97488999999999, "longitude": 7.1954365, "race": "Kerzerslauf", "date": {"sam. 15.03.2014": {"year": 2014, "day": 15, "month": 3, "categories": {"15-M45": {"distance": 15, "rank": 483, "pace": 325000000000, "time": 4879.3}}, "weekday": "saturday", "livingplace": "Sarnen"}}, "location": "Kerzers"}}, "birth": 1968}