{"name": "Lang Roland", "sex": "M", "races": {"Dreil\u00e4nder-Lauf, Basel": {"latitude": 47.5595986, "longitude": 7.5885761, "race": "Dreil\u00e4nder-Lauf, Basel", "date": {"dim. 20.05.2012": {"year": 2012, "day": 20, "month": 5, "categories": {"10M40": {"distance": 10, "rank": 33, "pace": 321000000000, "time": 3244.8}}, "weekday": "sunday", "livingplace": "Magden"}}, "location": "Basel"}, "Winterthur Marathon": {"latitude": 39.8088766, "longitude": -75.6037351, "race": "Winterthur Marathon", "date": {"dim. 26.05.2013": {"year": 2013, "day": 26, "month": 5, "categories": {"10-M40": {"distance": 10, "rank": 38, "pace": 316000000000, "time": 3163.0}}, "weekday": "sunday", "livingplace": "Magden"}}, "location": "Winterthur"}, "Basler Stadtlauf": {"latitude": 47.5595986, "longitude": 7.5885761, "race": "Basler Stadtlauf", "date": {"sam. 24.11.2007": {"year": 2007, "day": 24, "month": 11, "categories": {"M": {"distance": 6, "rank": 283, "pace": 290000000000, "time": 1598.5}}, "weekday": "saturday", "livingplace": "Magden"}, "sam. 25.11.2006": {"year": 2006, "day": 25, "month": 11, "categories": {"M": {"distance": 6, "rank": 280, "pace": 292000000000, "time": 1606.5}}, "weekday": "saturday", "livingplace": "Magden"}}, "location": "Basel"}}, "birth": 1970}