{"name": "Largier Michel", "sex": "M", "races": {"Walliseller Lauf, Wallisellen": {"latitude": NaN, "longitude": NaN, "race": "Walliseller Lauf, Wallisellen", "date": {"dim. 06.11.2005": {"year": 2005, "day": 6, "month": 11, "categories": {"M8": {"distance": 2, "rank": 34, "pace": 273000000000, "time": 532.6}}, "weekday": "sunday", "livingplace": "Langnau am Albis"}, "dim. 02.11.2003": {"year": 2003, "day": 2, "month": 11, "categories": {"M9": {"distance": 2, "rank": 20, "pace": 265000000000, "time": 517.1}}, "weekday": "sunday", "livingplace": "Langnau am Albis"}, "dim. 07.11.2004": {"year": 2004, "day": 7, "month": 11, "categories": {"M9": {"distance": 2, "rank": 24, "pace": 268000000000, "time": 523.8}}, "weekday": "sunday", "livingplace": "Langnau am Albis"}}, "location": "Wallisellen"}}, "birth": 1993}