{"name": "Leuenberger Ursula", "sex": "F", "races": {"Morat-Fribourg": {"latitude": 46.92922110000001, "longitude": 7.120184, "race": "Morat-Fribourg", "date": {"sam. 03.10.2015": {"year": 2015, "day": 3, "month": 10, "categories": {"17-W50": {"distance": 17, "rank": 127, "pace": 403000000000, "time": 6935.7}}, "weekday": "saturday", "livingplace": "Torbel"}, "sam. 06.10.2012": {"year": 2012, "day": 6, "month": 10, "categories": {"17-W45": {"distance": 17, "rank": 235, "pace": 414000000000, "time": 7240.7}}, "weekday": "saturday", "livingplace": "Torbel"}, "sam. 04.10.2014": {"year": 2014, "day": 4, "month": 10, "categories": {"17-W50": {"distance": 17, "rank": 140, "pace": 416000000000, "time": 7146.3}}, "weekday": "saturday", "livingplace": "Torbel"}}, "location": "Murten"}, "Schweizer Frauenlauf Bern": {"latitude": 46.9479739, "longitude": 7.4474468, "race": "Schweizer Frauenlauf Bern", "date": {"dim. 10.06.2012": {"year": 2012, "day": 10, "month": 6, "categories": {"5-W45": {"distance": 5, "rank": 68, "pace": 296000000000, "time": 1482.2}}, "weekday": "sunday", "livingplace": "Brugger Antli"}}, "location": "Bern"}, "Badener Limmat-Lauf, Baden": {"latitude": 48.5699281, "longitude": 8.5303972, "race": "Badener Limmat-Lauf, Baden", "date": {"sam. 29.03.2008": {"year": 2008, "day": 29, "month": 3, "categories": {"F40": {"distance": 13, "rank": 37, "pace": 339000000000, "time": 4485.9}}, "weekday": "saturday", "livingplace": "Baden"}, "sam. 28.03.2009": {"year": 2009, "day": 28, "month": 3, "categories": {"F40": {"distance": 13, "rank": 22, "pace": 315000000000, "time": 4162.7}}, "weekday": "saturday", "livingplace": "Baden"}}, "location": "Baden"}, "Aletsch-Halbmarathon, Bettmeralp": {"latitude": NaN, "longitude": NaN, "race": "Aletsch-Halbmarathon, Bettmeralp", "date": {"dim. 29.06.2014": {"year": 2014, "day": 29, "month": 6, "categories": {"F50": {"distance": 13, "rank": 51, "pace": 500000000000, "time": 6657.7}}, "weekday": "sunday", "livingplace": "Torbel"}, "dim. 28.06.2015": {"year": 2015, "day": 28, "month": 6, "categories": {"F50": {"distance": 21, "rank": 79, "pace": 679000000000, "time": 14340.9}}, "weekday": "sunday", "livingplace": "Torbel"}}, "location": "Bettmeralp"}, "Hallwilerseelauf, Beinwil am See": {"latitude": NaN, "longitude": NaN, "race": "Hallwilerseelauf, Beinwil am See", "date": {"sam. 16.10.2010": {"year": 2010, "day": 16, "month": 10, "categories": {"21-F40": {"distance": 21, "rank": 64, "pace": 301000000000, "time": 6357.3}}, "weekday": "saturday", "livingplace": "Baden"}, "sam. 14.10.2006": {"year": 2006, "day": 14, "month": 10, "categories": {"F40": {"distance": 21, "rank": 102, "pace": 320000000000, "time": 6761.4}}, "weekday": "saturday", "livingplace": "Dattwil"}, "sam. 10.10.2009": {"year": 2009, "day": 10, "month": 10, "categories": {"21-F40": {"distance": 21, "rank": 106, "pace": 318000000000, "time": 6725.6}}, "weekday": "saturday", "livingplace": "Baden"}}, "location": "Beinwil am See"}, "Z\u00fcrcher Silvesterlauf, Z\u00fcrich": {"latitude": 47.3768866, "longitude": 8.541694, "race": "Z\u00fcrcher Silvesterlauf, Z\u00fcrich", "date": {"dim. 10.12.2006": {"year": 2006, "day": 10, "month": 12, "categories": {"DaAK2-8": {"distance": 9, "rank": 113, "pace": 294000000000, "time": 2530.0}}, "weekday": "sunday", "livingplace": "Dattwil"}, "dim. 16.12.2007": {"year": 2007, "day": 16, "month": 12, "categories": {"DaAK2-8": {"distance": 9, "rank": 134, "pace": 303000000000, "time": 2610.3}}, "weekday": "sunday", "livingplace": "Dattwil"}}, "location": "Z\u00fcrich"}, "Int Greifenseelauf, Uster": {"latitude": 47.3482747, "longitude": 8.717873899999999, "race": "Int Greifenseelauf, Uster", "date": {"sam. 20.09.2003": {"year": 2003, "day": 20, "month": 9, "categories": {"H/W40": {"distance": 21, "rank": 150, "pace": 360000000000, "time": 7604.5}}, "weekday": "saturday", "livingplace": "Dattwil"}, "sam. 17.09.2005": {"year": 2005, "day": 17, "month": 9, "categories": {"H/W40": {"distance": 21, "rank": 187, "pace": 323000000000, "time": 6822.4}}, "weekday": "saturday", "livingplace": "Dattwil"}, "sam. 18.09.2004": {"year": 2004, "day": 18, "month": 9, "categories": {"H/W40": {"distance": 21, "rank": 160, "pace": 332000000000, "time": 7024.3}}, "weekday": "saturday", "livingplace": "Dattwil"}}, "location": "Uster"}}, "birth": 1963}