{"name": "Mathis Armin", "sex": "M", "races": {"Z\u00fcrich Marathon, Teamrun und Cityrun": {"latitude": 47.3768866, "longitude": 8.541694, "race": "Z\u00fcrich Marathon, Teamrun und Cityrun", "date": {"dim. 04.04.2004": {"year": 2004, "day": 4, "month": 4, "categories": {"M30": {"distance": 42, "rank": 96, "pace": 246000000000, "time": 10405.6}}, "weekday": "sunday", "livingplace": "Chur"}}, "location": "Z\u00fcrich"}, "Kerzerslauf": {"latitude": 46.97488999999999, "longitude": 7.1954365, "race": "Kerzerslauf", "date": {"sam. 15.03.2003": {"year": 2003, "day": 15, "month": 3, "categories": {"M20": {"distance": 15, "rank": 126, "pace": 235000000000, "time": 3529.3}}, "weekday": "saturday", "livingplace": "Chur"}, "sam. 20.03.2004": {"year": 2004, "day": 20, "month": 3, "categories": {"M35": {"distance": 15, "rank": 75, "pace": 244000000000, "time": 3664.0}}, "weekday": "saturday", "livingplace": "Chur"}, "sam. 19.03.2005": {"year": 2005, "day": 19, "month": 3, "categories": {"M35": {"distance": 15, "rank": 74, "pace": 253000000000, "time": 3804.6}}, "weekday": "saturday", "livingplace": "Chur"}, "sam. 17.03.2007": {"year": 2007, "day": 17, "month": 3, "categories": {"M35": {"distance": 15, "rank": 97, "pace": 244000000000, "time": 3669.7}}, "weekday": "saturday", "livingplace": "Chur"}}, "location": "Kerzers"}, "Jungfrau-Marathon, Interlaken": {"latitude": NaN, "longitude": NaN, "race": "Jungfrau-Marathon, Interlaken", "date": {"sam. 06.09.2003": {"year": 2003, "day": 6, "month": 9, "categories": {"M20": {"distance": 42, "rank": 167, "pace": 360000000000, "time": 15190.2}}, "weekday": "saturday", "livingplace": "Chur"}}, "location": "Interlaken"}}, "birth": 1969}