{"name": "Moser Christophe", "sex": "M", "races": {"Morat-Fribourg": {"latitude": 46.92922110000001, "longitude": 7.120184, "race": "Morat-Fribourg", "date": {"sam. 02.10.2010": {"year": 2010, "day": 2, "month": 10, "categories": {"17-M20": {"distance": 17, "rank": 290, "pace": 265000000000, "time": 4563.6}}, "weekday": "saturday", "livingplace": "Tuttwil"}, "dim. 05.10.2003": {"year": 2003, "day": 5, "month": 10, "categories": {"CadH": {"distance": 17, "rank": 22, "pace": 278000000000, "time": 4775.3}}, "weekday": "sunday", "livingplace": "Tuttwil"}, "sam. 06.10.2012": {"year": 2012, "day": 6, "month": 10, "categories": {"17-M20": {"distance": 17, "rank": 216, "pace": 255000000000, "time": 4463.1}}, "weekday": "saturday", "livingplace": "Frauenfeld"}}, "location": "Murten"}}, "birth": 1987}