{"name": "N\u00e4scher Basil", "sex": "M", "races": {"Wylandlauf, Andelfingen": {"latitude": NaN, "longitude": NaN, "race": "Wylandlauf, Andelfingen", "date": {"sam. 14.06.2008": {"year": 2008, "day": 14, "month": 6, "categories": {"U": {"distance": 2, "rank": 2, "pace": 218000000000, "time": 404.8}}, "weekday": "saturday", "livingplace": "Lag"}}, "location": "Andelfingen"}, "Campionati Svizzeri di Cross, Tenero": {"latitude": NaN, "longitude": NaN, "race": "Campionati Svizzeri di Cross, Tenero", "date": {"sam. 08.03.2008": {"year": 2008, "day": 8, "month": 3, "categories": {"U12M": {"distance": 2, "rank": 4, "pace": 226000000000, "time": 453.2}}, "weekday": "saturday", "livingplace": "St. Gallen"}}, "location": "Tenero"}, "Laufsporttag Winterthur": {"latitude": 39.8088766, "longitude": -75.6037351, "race": "Laufsporttag Winterthur", "date": {"sam. 01.03.2008": {"year": 2008, "day": 1, "month": 3, "categories": {"U": {"distance": 2, "rank": 2, "pace": 217000000000, "time": 412.8}}, "weekday": "saturday", "livingplace": "Lag"}}, "location": "Winterthur"}, "Zumiker-Lauf": {"latitude": NaN, "longitude": NaN, "race": "Zumiker-Lauf", "date": {"sam. 24.05.2008": {"year": 2008, "day": 24, "month": 5, "categories": {"U": {"distance": 2, "rank": 2, "pace": 110000000000, "time": 204.3}}, "weekday": "saturday", "livingplace": "Lag"}}, "location": "Zumikon"}, "Dietiker Neujahrslauf, Dietikon": {"latitude": 47.4053885, "longitude": 8.39977, "race": "Dietiker Neujahrslauf, Dietikon", "date": {"sam. 12.01.2008": {"year": 2008, "day": 12, "month": 1, "categories": {"U": {"distance": 2, "rank": 1, "pace": 219000000000, "time": 395.5}}, "weekday": "saturday", "livingplace": "Gossau"}}, "location": "Dietikon"}, "Hallwilerseelauf, Beinwil am See": {"latitude": NaN, "longitude": NaN, "race": "Hallwilerseelauf, Beinwil am See", "date": {"sam. 12.10.2013": {"year": 2013, "day": 12, "month": 10, "categories": {"10-MJA": {"distance": 10, "rank": 5, "pace": 225000000000, "time": 2257.4}}, "weekday": "saturday", "livingplace": "St. Gallen"}, "sam. 10.10.2015": {"year": 2015, "day": 10, "month": 10, "categories": {"21-Mjun": {"distance": 21, "rank": 5, "pace": 250000000000, "time": 5281.8}}, "weekday": "saturday", "livingplace": "St. Gallen"}, "sam. 14.10.2006": {"year": 2006, "day": 14, "month": 10, "categories": {"MJun": {"distance": 21, "rank": 33, "pace": 315000000000, "time": 6666.6}}, "weekday": "saturday", "livingplace": "St. Gallen"}}, "location": "Beinwil am See"}, "Z\u00fcrcher Silvesterlauf, Z\u00fcrich": {"latitude": 47.3768866, "longitude": 8.541694, "race": "Z\u00fcrcher Silvesterlauf, Z\u00fcrich", "date": {"dim. 13.12.2009": {"year": 2009, "day": 13, "month": 12, "categories": {"Sch\u00fcA-M": {"distance": 1, "rank": 3, "pace": 197000000000, "time": 277.1}}, "weekday": "sunday", "livingplace": "St. Gallen"}, "dim. 11.12.2011": {"year": 2011, "day": 11, "month": 12, "categories": {"Knaben B": {"distance": 3, "rank": 17, "pace": 226000000000, "time": 587.9}}, "weekday": "sunday", "livingplace": "St. Gallen"}, "dim. 16.12.2007": {"year": 2007, "day": 16, "month": 12, "categories": {"Sch\u00fcB-M": {"distance": 1, "rank": 3, "pace": 202000000000, "time": 283.5}}, "weekday": "sunday", "livingplace": "St. Gallen"}}, "location": "Z\u00fcrich"}, "St  Galler Altstadtlauf": {"latitude": 47.4244818, "longitude": 9.3767173, "race": "St  Galler Altstadtlauf", "date": {"sam. 23.09.2006": {"year": 2006, "day": 23, "month": 9, "categories": {"SDM": {"distance": 2, "rank": 2, "pace": 224000000000, "time": 415.1}}, "weekday": "saturday", "livingplace": "St. Gallen"}, "sam. 17.09.2005": {"year": 2005, "day": 17, "month": 9, "categories": {"SEM": {"distance": 2, "rank": 2, "pace": 242000000000, "time": 363.7}}, "weekday": "saturday", "livingplace": "St. Gallen"}}, "location": "St. Gallen"}}, "birth": 1997}