{"name": "Niederberger Kevin", "sex": "M", "races": {"Lenzburger Lauf": {"latitude": 47.3904443, "longitude": 8.172154500000001, "race": "Lenzburger Lauf", "date": {"sam. 19.05.2007": {"year": 2007, "day": 19, "month": 5, "categories": {"JMB": {"distance": 2, "rank": 5, "pace": 200000000000, "time": 440.1}}, "weekday": "saturday", "livingplace": "Emmenstrand"}}, "location": "Lenzburg"}, "Rotseelauf, Ebikon": {"latitude": NaN, "longitude": NaN, "race": "Rotseelauf, Ebikon", "date": {"sam. 21.04.2007": {"year": 2007, "day": 21, "month": 4, "categories": {"M14": {"distance": 2, "rank": 14, "pace": 220000000000, "time": 484.9}}, "weekday": "saturday", "livingplace": "Emmenstrand"}}, "location": "Ebikon"}, "Hellebardenlauf Sempach": {"latitude": NaN, "longitude": NaN, "race": "Hellebardenlauf Sempach", "date": {"sam. 30.06.2007": {"year": 2007, "day": 30, "month": 6, "categories": {"5.8k/JKA": {"distance": 6, "rank": 5, "pace": 241000000000, "time": 1400.6}}, "weekday": "saturday", "livingplace": "Emmenstrand"}}, "location": "Sempach Stadt"}, "Herbstlauf Muri AG": {"latitude": NaN, "longitude": NaN, "race": "Herbstlauf Muri AG", "date": {"sam. 25.08.2007": {"year": 2007, "day": 25, "month": 8, "categories": {"32": {"distance": 4, "rank": 24, "pace": 452000000000, "time": 1765.9}}, "weekday": "saturday", "livingplace": "Boswil"}}, "location": "Muri AG"}}, "birth": 1992}