{"name": "Pulver Peter", "sex": "M", "races": {"SwissCityMarathon - Lucerne, Luzern": {"latitude": 47.05016819999999, "longitude": 8.3093072, "race": "SwissCityMarathon - Lucerne, Luzern", "date": {"dim. 26.10.2014": {"year": 2014, "day": 26, "month": 10, "categories": {"H-M50": {"distance": 21, "rank": 281, "pace": 305000000000, "time": 6443.6}}, "weekday": "sunday", "livingplace": "Thalwil"}, "dim. 27.10.2013": {"year": 2013, "day": 27, "month": 10, "categories": {"H-M50": {"distance": 21, "rank": 340, "pace": 317000000000, "time": 6698.4}}, "weekday": "sunday", "livingplace": "Thalwil"}}, "location": "Luzern"}, "ASICS Bremgarter Reusslauf": {"latitude": 47.34917739999999, "longitude": 8.3397905, "race": "ASICS Bremgarter Reusslauf", "date": {"sam. 28.02.2015": {"year": 2015, "day": 28, "month": 2, "categories": {"11-M50": {"distance": 11, "rank": 153, "pace": 272000000000, "time": 2997.7}}, "weekday": "saturday", "livingplace": "Thalwil"}}, "location": "Bremgarten AG"}, "Eiger Ultra Trail, Grindelwald": {"latitude": 46.624164, "longitude": 8.0413962, "race": "Eiger Ultra Trail, Grindelwald", "date": {"sam. 19.07.2014": {"year": 2014, "day": 19, "month": 7, "categories": {"C-HS2": {"distance": 16, "rank": 17, "pace": 668000000000, "time": 10695.3}}, "weekday": "saturday", "livingplace": "Thalwil"}}, "location": "Grindelwald"}, "Sempacherseelauf, Sursee": {"latitude": NaN, "longitude": NaN, "race": "Sempacherseelauf, Sursee", "date": {"sam. 24.05.2014": {"year": 2014, "day": 24, "month": 5, "categories": {"21M50": {"distance": 21, "rank": 82, "pace": 304000000000, "time": 6414.7}}, "weekday": "saturday", "livingplace": "Thalwil"}}, "location": "Sursee"}, "Hallwilerseelauf, Beinwil am See": {"latitude": NaN, "longitude": NaN, "race": "Hallwilerseelauf, Beinwil am See", "date": {"sam. 12.10.2013": {"year": 2013, "day": 12, "month": 10, "categories": {"21-M50": {"distance": 21, "rank": 280, "pace": 312000000000, "time": 6603.5}}, "weekday": "saturday", "livingplace": "Thalwil"}, "sam. 11.10.2014": {"year": 2014, "day": 11, "month": 10, "categories": {"21-M50": {"distance": 21, "rank": 241, "pace": 308000000000, "time": 6518.7}}, "weekday": "saturday", "livingplace": "Thalwil"}}, "location": "Beinwil am See"}, "Z\u00fcrcher Silvesterlauf, Z\u00fcrich": {"latitude": 47.3768866, "longitude": 8.541694, "race": "Z\u00fcrcher Silvesterlauf, Z\u00fcrich", "date": {"dim. 12.12.2010": {"year": 2010, "day": 12, "month": 12, "categories": {"8-MenAK2": {"distance": 9, "rank": 1243, "pace": 352000000000, "time": 3030.2}}, "weekday": "sunday", "livingplace": "Thalwil"}, "dim. 15.12.2013": {"year": 2013, "day": 15, "month": 12, "categories": {"10-M50": {"distance": 10, "rank": 549, "pace": 333000000000, "time": 3338.2}}, "weekday": "sunday", "livingplace": "Thalwil"}, "dim. 16.12.2012": {"year": 2012, "day": 16, "month": 12, "categories": {"8-MM50": {"distance": 9, "rank": 537, "pace": 341000000000, "time": 2937.3}}, "weekday": "sunday", "livingplace": "Thalwil"}, "dim. 11.12.2011": {"year": 2011, "day": 11, "month": 12, "categories": {"8-MenAK2": {"distance": 9, "rank": 1176, "pace": 348000000000, "time": 3000.8}}, "weekday": "sunday", "livingplace": "Thalwil"}, "dim. 14.12.2014": {"year": 2014, "day": 14, "month": 12, "categories": {"10-M50": {"distance": 10, "rank": 569, "pace": 330000000000, "time": 3305.0}}, "weekday": "sunday", "livingplace": "Thalwil"}, "dim. 13.12.2009": {"year": 2009, "day": 13, "month": 12, "categories": {"8-MenAK2": {"distance": 9, "rank": 1310, "pace": 361000000000, "time": 3105.2}}, "weekday": "sunday", "livingplace": "Thalwil"}}, "location": "Z\u00fcrich"}, "Sihltaler Fr\u00fchlingslauf, Gattikon": {"latitude": 47.2949282, "longitude": 8.5644799, "race": "Sihltaler Fr\u00fchlingslauf, Gattikon", "date": {"mer. 01.05.2013": {"year": 2013, "day": 1, "month": 5, "categories": {"10-M50": {"distance": 10, "rank": 53, "pace": 318000000000, "time": 3188.8}}, "weekday": "wednesday", "livingplace": "Thalwil"}, "jeu. 01.05.2014": {"year": 2014, "day": 1, "month": 5, "categories": {"10-M50": {"distance": 10, "rank": 55, "pace": 302000000000, "time": 3023.6}}, "weekday": "thursday", "livingplace": "Thalwil"}}, "location": "Gattikon"}, "Z\u00fcrich Marathon, Teamrun und Cityrun": {"latitude": 47.3768866, "longitude": 8.541694, "race": "Z\u00fcrich Marathon, Teamrun und Cityrun", "date": {"dim. 22.04.2012": {"year": 2012, "day": 22, "month": 4, "categories": {"10-M50": {"distance": 10, "rank": 64, "pace": 313000000000, "time": 3136.8}}, "weekday": "sunday", "livingplace": "Thalwil"}, "dim. 06.04.2014": {"year": 2014, "day": 6, "month": 4, "categories": {"10-M50": {"distance": 10, "rank": 52, "pace": 285000000000, "time": 2795.2}}, "weekday": "sunday", "livingplace": "Thalwil"}, "dim. 07.04.2013": {"year": 2013, "day": 7, "month": 4, "categories": {"10-M50": {"distance": 10, "rank": 76, "pace": 298000000000, "time": 2988.4}}, "weekday": "sunday", "livingplace": "Thalwil"}, "dim. 19.04.2015": {"year": 2015, "day": 19, "month": 4, "categories": {"42-M50": {"distance": 42, "rank": 189, "pace": 337000000000, "time": 14242.0}}, "weekday": "sunday", "livingplace": "Thalwil"}}, "location": "Z\u00fcrich"}}, "birth": 1962}