{"name": "Renfer Sarah", "sex": "F", "races": {"Z\u00fcrich Marathon, Teamrun und Cityrun": {"latitude": 47.3768866, "longitude": 8.541694, "race": "Z\u00fcrich Marathon, Teamrun und Cityrun", "date": {"dim. 22.04.2012": {"year": 2012, "day": 22, "month": 4, "categories": {"10-W20": {"distance": 10, "rank": 196, "pace": 417000000000, "time": 4173.2}}, "weekday": "sunday", "livingplace": "Zurich"}, "dim. 07.04.2013": {"year": 2013, "day": 7, "month": 4, "categories": {"10-W20": {"distance": 10, "rank": 250, "pace": 383000000000, "time": 3839.8}}, "weekday": "sunday", "livingplace": "Zurich"}}, "location": "Z\u00fcrich"}, "Aletsch-Halbmarathon, Bettmeralp": {"latitude": NaN, "longitude": NaN, "race": "Aletsch-Halbmarathon, Bettmeralp", "date": {"dim. 28.06.2015": {"year": 2015, "day": 28, "month": 6, "categories": {"F20": {"distance": 21, "rank": 222, "pace": 622000000000, "time": 13124.9}}, "weekday": "sunday", "livingplace": "Zurich"}}, "location": "Bettmeralp"}, "Z\u00fcrcher Silvesterlauf, Z\u00fcrich": {"latitude": 47.3768866, "longitude": 8.541694, "race": "Z\u00fcrcher Silvesterlauf, Z\u00fcrich", "date": {"dim. 15.12.2013": {"year": 2013, "day": 15, "month": 12, "categories": {"10-F20": {"distance": 10, "rank": 744, "pace": 399000000000, "time": 3995.0}}, "weekday": "sunday", "livingplace": "Zurich"}}, "location": "Z\u00fcrich"}, "Schweizer Frauenlauf Bern": {"latitude": 46.9479739, "longitude": 7.4474468, "race": "Schweizer Frauenlauf Bern", "date": {"dim. 10.06.2012": {"year": 2012, "day": 10, "month": 6, "categories": {"5-W20": {"distance": 5, "rank": 867, "pace": 379000000000, "time": 1899.3}}, "weekday": "sunday", "livingplace": "Zurich"}, "dim. 13.06.2010": {"year": 2010, "day": 13, "month": 6, "categories": {"5-W20": {"distance": 5, "rank": 704, "pace": 385000000000, "time": 1928.0}}, "weekday": "sunday", "livingplace": "Zurich"}, "dim. 09.06.2013": {"year": 2013, "day": 9, "month": 6, "categories": {"5-W20": {"distance": 5, "rank": 691, "pace": 365000000000, "time": 1828.3}}, "weekday": "sunday", "livingplace": "Zurich"}, "dim. 14.06.2009": {"year": 2009, "day": 14, "month": 6, "categories": {"5-W20": {"distance": 5, "rank": 954, "pace": 451000000000, "time": 2256.8}}, "weekday": "sunday", "livingplace": "Lengnau"}, "dim. 14.06.2015": {"year": 2015, "day": 14, "month": 6, "categories": {"5-W30": {"distance": 5, "rank": 299, "pace": 369000000000, "time": 1847.8}}, "weekday": "sunday", "livingplace": "Zurich"}}, "location": "Bern"}}, "birth": 1984}