{"name": "R\u00fcedlinger Andreas", "sex": "M", "races": {"ASICS Bremgarter Reusslauf": {"latitude": 47.34917739999999, "longitude": 8.3397905, "race": "ASICS Bremgarter Reusslauf", "date": {"sam. 26.02.2011": {"year": 2011, "day": 26, "month": 2, "categories": {"M20": {"distance": 11, "rank": 10, "pace": 190000000000, "time": 2095.3}}, "weekday": "saturday", "livingplace": "Bulach"}, "sam. 22.02.2003": {"year": 2003, "day": 22, "month": 2, "categories": {"11": {"distance": 11, "rank": 40, "pace": 207000000000, "time": 2281.8}}, "weekday": "saturday", "livingplace": "Glattbrugg"}}, "location": "Bremgarten AG"}, "Basler Stadtlauf": {"latitude": 47.5595986, "longitude": 7.5885761, "race": "Basler Stadtlauf", "date": {"sam. 29.11.2014": {"year": 2014, "day": 29, "month": 11, "categories": {"Elite M": {"distance": 8, "rank": 31, "pace": 193000000000, "time": 1457.8}}, "weekday": "saturday", "livingplace": "Winterthur"}, "sam. 30.11.2013": {"year": 2013, "day": 30, "month": 11, "categories": {"EliteM": {"distance": 8, "rank": 33, "pace": 190000000000, "time": 1437.5}}, "weekday": "saturday", "livingplace": "Winterthur"}}, "location": "Basel"}, "Steinh\u00f6lzlilauf, Liebefeld": {"latitude": 46.933331, "longitude": 7.416668, "race": "Steinh\u00f6lzlilauf, Liebefeld", "date": {"dim. 06.12.2009": {"year": 2009, "day": 6, "month": 12, "categories": {"HauptM": {"distance": 11, "rank": 4, "pace": 210000000000, "time": 2210.0}}, "weekday": "sunday", "livingplace": "Bulach"}}, "location": "Liebefeld"}, "Flughafenlauf, Kloten": {"latitude": NaN, "longitude": NaN, "race": "Flughafenlauf, Kloten", "date": {"jeu. 21.05.2009": {"year": 2009, "day": 21, "month": 5, "categories": {"A": {"distance": 17, "rank": 3, "pace": 204000000000, "time": 3476.0}}, "weekday": "thursday", "livingplace": "Regensdorf"}}, "location": "Kloten"}, "Kyburglauf, Kyburg": {"latitude": NaN, "longitude": NaN, "race": "Kyburglauf, Kyburg", "date": {"sam. 09.11.2013": {"year": 2013, "day": 9, "month": 11, "categories": {"10-M20": {"distance": 10, "rank": 2, "pace": 226000000000, "time": 2267.1}}, "weekday": "saturday", "livingplace": "Winterthur"}}, "location": "Kyburg"}, "Gel\u00e4ndelauf am Bachtel, D\u00fcrnten": {"latitude": NaN, "longitude": NaN, "race": "Gel\u00e4ndelauf am Bachtel, D\u00fcrnten", "date": {"dim. 29.06.2014": {"year": 2014, "day": 29, "month": 6, "categories": {"A": {"distance": 12, "rank": 2, "pace": 209000000000, "time": 2538.1}}, "weekday": "sunday", "livingplace": "Winterthur"}}, "location": "D\u00fcrnten"}, "Z\u00fcrcher Silvesterlauf, Z\u00fcrich": {"latitude": 47.3768866, "longitude": 8.541694, "race": "Z\u00fcrcher Silvesterlauf, Z\u00fcrich", "date": {"dim. 15.12.2013": {"year": 2013, "day": 15, "month": 12, "categories": {"Elite M": {"distance": 9, "rank": 30, "pace": 187000000000, "time": 1690.5}}, "weekday": "sunday", "livingplace": "Winterthur"}, "dim. 14.12.2014": {"year": 2014, "day": 14, "month": 12, "categories": {"Elite M": {"distance": 9, "rank": 28, "pace": 188000000000, "time": 1695.2}}, "weekday": "sunday", "livingplace": "Winterthur"}}, "location": "Z\u00fcrich"}, "Campionati Svizzeri di Cross, Tenero": {"latitude": NaN, "longitude": NaN, "race": "Campionati Svizzeri di Cross, Tenero", "date": {"sam. 08.03.2008": {"year": 2008, "day": 8, "month": 3, "categories": {"Men": {"distance": 10, "rank": 27, "pace": 209000000000, "time": 2090.4}}, "weekday": "saturday", "livingplace": "Bulach"}}, "location": "Tenero"}}, "birth": 1985}