{"name": "Stoller Henri", "sex": "M", "races": {"Hallwilerseelauf, Beinwil am See": {"latitude": NaN, "longitude": NaN, "race": "Hallwilerseelauf, Beinwil am See", "date": {"sam. 12.10.2013": {"year": 2013, "day": 12, "month": 10, "categories": {"10-Mann": {"distance": 10, "rank": 549, "pace": 391000000000, "time": 3917.4}}, "weekday": "saturday", "livingplace": "Bevilard"}, "sam. 13.10.2012": {"year": 2012, "day": 13, "month": 10, "categories": {"10-Mann": {"distance": 10, "rank": 424, "pace": 384000000000, "time": 3842.6}}, "weekday": "saturday", "livingplace": "Bevilard"}}, "location": "Beinwil am See"}}, "birth": 1954}