{"name": "Sumi Arthur", "sex": "M", "races": {"Gippinger Stauseelauf": {"latitude": 47.5810513, "longitude": 8.2152586, "race": "Gippinger Stauseelauf", "date": {"lun. 31.12.2001": {"year": 2001, "day": 31, "month": 12, "categories": {"13": {"distance": 8, "rank": 309, "pace": 309000000000, "time": 2380.5}}, "weekday": "monday", "livingplace": "Wigoltingen"}, "mar. 31.12.2002": {"year": 2002, "day": 31, "month": 12, "categories": {"M40": {"distance": 8, "rank": 336, "pace": 327000000000, "time": 2454.7}}, "weekday": "tuesday", "livingplace": "Wigoltingen"}, "jeu. 31.12.2015": {"year": 2015, "day": 31, "month": 12, "categories": {"7-M60": {"distance": 8, "rank": 67, "pace": 345000000000, "time": 2602.3}}, "weekday": "thursday", "livingplace": "Wigoltingen"}, "lun. 31.12.2007": {"year": 2007, "day": 31, "month": 12, "categories": {"M50": {"distance": 8, "rank": 166, "pace": 318000000000, "time": 2400.3}}, "weekday": "monday", "livingplace": "Wigoltingen"}}, "location": "Leuggern"}, "Luzerner Stadtlauf": {"latitude": 47.05016819999999, "longitude": 8.3093072, "race": "Luzerner Stadtlauf", "date": {"sam. 03.05.2003": {"year": 2003, "day": 3, "month": 5, "categories": {"K/29": {"distance": 6, "rank": 109, "pace": 318000000000, "time": 1749.5}}, "weekday": "saturday", "livingplace": "Wigoltingen"}}, "location": "Luzern"}, "Morat-Fribourg": {"latitude": 46.92922110000001, "longitude": 7.120184, "race": "Morat-Fribourg", "date": {"dim. 05.10.2003": {"year": 2003, "day": 5, "month": 10, "categories": {"M50": {"distance": 17, "rank": 355, "pace": 343000000000, "time": 5903.8}}, "weekday": "sunday", "livingplace": "Wigoltingen"}, "dim. 07.10.2001": {"year": 2001, "day": 7, "month": 10, "categories": {"M45": {"distance": 17, "rank": 566, "pace": 376000000000, "time": 6470.6}}, "weekday": "sunday", "livingplace": "Wigoltingen"}, "dim. 06.10.2002": {"year": 2002, "day": 6, "month": 10, "categories": {"M45": {"distance": 17, "rank": 547, "pace": 358000000000, "time": 6162.8}}, "weekday": "sunday", "livingplace": "Wigoltingen"}}, "location": "Murten"}, "Basler Stadtlauf": {"latitude": 47.5595986, "longitude": 7.5885761, "race": "Basler Stadtlauf", "date": {"sam. 24.11.2007": {"year": 2007, "day": 24, "month": 11, "categories": {"V": {"distance": 6, "rank": 231, "pace": 311000000000, "time": 1715.5}}, "weekday": "saturday", "livingplace": "Wigoltingen"}, "sam. 29.11.2008": {"year": 2008, "day": 29, "month": 11, "categories": {"Y": {"distance": 6, "rank": 135, "pace": 317000000000, "time": 1744.3}}, "weekday": "saturday", "livingplace": "Wigoltingen"}, "sam. 30.11.2002": {"year": 2002, "day": 30, "month": 11, "categories": {"U": {"distance": 6, "rank": 282, "pace": 328000000000, "time": 1806.6}}, "weekday": "saturday", "livingplace": "Wigoltingen"}, "sam. 29.11.2003": {"year": 2003, "day": 29, "month": 11, "categories": {"V": {"distance": 6, "rank": 194, "pace": 312000000000, "time": 1718.0}}, "weekday": "saturday", "livingplace": "Wigoltingen"}, "sam. 25.11.2006": {"year": 2006, "day": 25, "month": 11, "categories": {"V": {"distance": 6, "rank": 209, "pace": 307000000000, "time": 1689.1}}, "weekday": "saturday", "livingplace": "Wigoltingen"}, "sam. 26.11.2005": {"year": 2005, "day": 26, "month": 11, "categories": {"V": {"distance": 6, "rank": 209, "pace": 307000000000, "time": 1693.1}}, "weekday": "saturday", "livingplace": "Wigoltingen"}, "sam. 27.11.2004": {"year": 2004, "day": 27, "month": 11, "categories": {"V": {"distance": 6, "rank": 177, "pace": 301000000000, "time": 1657.2}}, "weekday": "saturday", "livingplace": "Wigoltingen"}}, "location": "Basel"}, "Hallwilerseelauf, Beinwil am See": {"latitude": NaN, "longitude": NaN, "race": "Hallwilerseelauf, Beinwil am See", "date": {"sam. 12.10.2013": {"year": 2013, "day": 12, "month": 10, "categories": {"21-M60": {"distance": 21, "rank": 138, "pace": 392000000000, "time": 8277.9}}, "weekday": "saturday", "livingplace": "Wigoltingen"}}, "location": "Beinwil am See"}, "SM CS 10km Strasse route + Volkslauf 10km, Uster": {"latitude": 47.3482747, "longitude": 8.717873899999999, "race": "SM CS 10km Strasse route + Volkslauf 10km, Uster", "date": {"sam. 23.03.2013": {"year": 2013, "day": 23, "month": 3, "categories": {"10-M60": {"distance": 10, "rank": 20, "pace": 320000000000, "time": 3206.3}}, "weekday": "saturday", "livingplace": "Wigoltingen"}}, "location": "Uster"}, "Dreil\u00e4nder-Lauf, Basel": {"latitude": 47.5595986, "longitude": 7.5885761, "race": "Dreil\u00e4nder-Lauf, Basel", "date": {"dim. 20.05.2012": {"year": 2012, "day": 20, "month": 5, "categories": {"21M50": {"distance": 21, "rank": 78, "pace": 355000000000, "time": 7497.1}}, "weekday": "sunday", "livingplace": "Wiboltingen"}}, "location": "Basel"}, "Z\u00fcrcher Silvesterlauf, Z\u00fcrich": {"latitude": 47.3768866, "longitude": 8.541694, "race": "Z\u00fcrcher Silvesterlauf, Z\u00fcrich", "date": {"dim. 14.12.2008": {"year": 2008, "day": 14, "month": 12, "categories": {"MenAK3-8": {"distance": 9, "rank": 379, "pace": 319000000000, "time": 2745.5}}, "weekday": "sunday", "livingplace": "Engwang"}, "dim. 10.12.2006": {"year": 2006, "day": 10, "month": 12, "categories": {"MenAK3-8": {"distance": 9, "rank": 403, "pace": 313000000000, "time": 2695.9}}, "weekday": "sunday", "livingplace": "Engwang"}, "dim. 16.12.2007": {"year": 2007, "day": 16, "month": 12, "categories": {"MenAK3-4": {"distance": 4, "rank": 28, "pace": 292000000000, "time": 1287.6}}, "weekday": "sunday", "livingplace": "Engwang"}}, "location": "Z\u00fcrich"}, "Sihltaler Fr\u00fchlingslauf, Gattikon": {"latitude": 47.2949282, "longitude": 8.5644799, "race": "Sihltaler Fr\u00fchlingslauf, Gattikon", "date": {"jeu. 01.05.2008": {"year": 2008, "day": 1, "month": 5, "categories": {"M50": {"distance": 10, "rank": 62, "pace": 333000000000, "time": 3335.6}}, "weekday": "thursday", "livingplace": "swiss masters running"}, "sam. 01.05.2010": {"year": 2010, "day": 1, "month": 5, "categories": {"M50": {"distance": 10, "rank": 57, "pace": 320000000000, "time": 3201.7}}, "weekday": "saturday", "livingplace": "Wigoltingen"}, "mar. 01.05.2012": {"year": 2012, "day": 1, "month": 5, "categories": {"10-M50": {"distance": 10, "rank": 63, "pace": 335000000000, "time": 3359.3}}, "weekday": "tuesday", "livingplace": "Wigoltingen"}, "mar. 01.05.2007": {"year": 2007, "day": 1, "month": 5, "categories": {"M50": {"distance": 10, "rank": 54, "pace": 326000000000, "time": 3262.5}}, "weekday": "tuesday", "livingplace": "Slvs"}}, "location": "Gattikon"}, "Glarner Stadtlauf, Glarus": {"latitude": NaN, "longitude": NaN, "race": "Glarner Stadtlauf, Glarus", "date": {"sam. 30.10.2010": {"year": 2010, "day": 30, "month": 10, "categories": {"7-Sen3": {"distance": 8, "rank": 23, "pace": 294000000000, "time": 2317.4}}, "weekday": "saturday", "livingplace": "Wigoltingen"}}, "location": "Glarus"}, "Lenzburger Lauf": {"latitude": 47.3904443, "longitude": 8.172154500000001, "race": "Lenzburger Lauf", "date": {"sam. 30.05.2015": {"year": 2015, "day": 30, "month": 5, "categories": {"W-M60": {"distance": 14, "rank": 15, "pace": 398000000000, "time": 5745.5}}, "weekday": "saturday", "livingplace": "Run Fit Thurgau"}, "sam. 24.05.2008": {"year": 2008, "day": 24, "month": 5, "categories": {"WM50": {"distance": 15, "rank": 23, "pace": 352000000000, "time": 5426.0}}, "weekday": "saturday", "livingplace": "Wigoltingen"}, "sam. 28.05.2011": {"year": 2011, "day": 28, "month": 5, "categories": {"W-M50": {"distance": 12, "rank": 23, "pace": 362000000000, "time": 4204.0}}, "weekday": "saturday", "livingplace": "Wigoltingen"}, "sam. 12.05.2012": {"year": 2012, "day": 12, "month": 5, "categories": {"W-M50": {"distance": 14, "rank": 24, "pace": 375000000000, "time": 5412.8}}, "weekday": "saturday", "livingplace": "Run Fit Thurgau"}, "sam. 19.05.2007": {"year": 2007, "day": 19, "month": 5, "categories": {"WM50": {"distance": 15, "rank": 30, "pace": 357000000000, "time": 5517.9}}, "weekday": "saturday", "livingplace": "Wigoltingen"}, "sam. 24.05.2014": {"year": 2014, "day": 24, "month": 5, "categories": {"W-M60": {"distance": 14, "rank": 18, "pace": 417000000000, "time": 6005.5}}, "weekday": "saturday", "livingplace": "Run Fit Thurgau"}, "sam. 29.05.2010": {"year": 2010, "day": 29, "month": 5, "categories": {"W-M50": {"distance": 14, "rank": 34, "pace": 411000000000, "time": 5927.9}}, "weekday": "saturday", "livingplace": "Wigoltingen"}, "sam. 25.05.2013": {"year": 2013, "day": 25, "month": 5, "categories": {"W-M60": {"distance": 14, "rank": 15, "pace": 400000000000, "time": 5770.3}}, "weekday": "saturday", "livingplace": "Run Fit Thurgau"}, "sam. 23.05.2009": {"year": 2009, "day": 23, "month": 5, "categories": {"WM50": {"distance": 14, "rank": 37, "pace": 434000000000, "time": 6259.3}}, "weekday": "saturday", "livingplace": "Wigoltingen"}}, "location": "Lenzburg"}, "10km Schweizer Meisterschaften Lyss": {"latitude": 47.0746504, "longitude": 7.3077022, "race": "10km Schweizer Meisterschaften Lyss", "date": {"sam. 02.04.2011": {"year": 2011, "day": 2, "month": 4, "categories": {"10-M55": {"distance": 10, "rank": 24, "pace": 324000000000, "time": 3245.6}}, "weekday": "saturday", "livingplace": "Wigoltingen"}, "sam. 31.03.2012": {"year": 2012, "day": 31, "month": 3, "categories": {"10-M55": {"distance": 10, "rank": 36, "pace": 324000000000, "time": 3240.0}}, "weekday": "saturday", "livingplace": "Wigoltingen"}}, "location": "Lyss"}, "Z\u00fcrich Marathon, Teamrun und Cityrun": {"latitude": 47.3768866, "longitude": 8.541694, "race": "Z\u00fcrich Marathon, Teamrun und Cityrun", "date": {"dim. 06.04.2014": {"year": 2014, "day": 6, "month": 4, "categories": {"42-M60": {"distance": 42, "rank": 68, "pace": 404000000000, "time": 17053.8}}, "weekday": "sunday", "livingplace": "Wigoltingen"}, "dim. 01.04.2007": {"year": 2007, "day": 1, "month": 4, "categories": {"M50": {"distance": 42, "rank": 409, "pace": 404000000000, "time": 17077.0}}, "weekday": "sunday", "livingplace": "Wigoltingen"}, "dim. 19.04.2015": {"year": 2015, "day": 19, "month": 4, "categories": {"42-M60": {"distance": 42, "rank": 72, "pace": 424000000000, "time": 17920.9}}, "weekday": "sunday", "livingplace": "Wigoltingen"}, "dim. 26.04.2009": {"year": 2009, "day": 26, "month": 4, "categories": {"M55": {"distance": 42, "rank": 233, "pace": 421000000000, "time": 17778.8}}, "weekday": "sunday", "livingplace": "Wigoltingen"}, "dim. 22.04.2012": {"year": 2012, "day": 22, "month": 4, "categories": {"42-M55": {"distance": 42, "rank": 173, "pace": 419000000000, "time": 17694.0}}, "weekday": "sunday", "livingplace": "Wigoltingen"}, "dim. 17.04.2011": {"year": 2011, "day": 17, "month": 4, "categories": {"42-M55": {"distance": 42, "rank": 179, "pace": 393000000000, "time": 16615.9}}, "weekday": "sunday", "livingplace": "Wigoltingen"}}, "location": "Z\u00fcrich"}, "Kerzerslauf": {"latitude": 46.97488999999999, "longitude": 7.1954365, "race": "Kerzerslauf", "date": {"sam. 18.03.2000": {"year": 2000, "day": 18, "month": 3, "categories": {"M45": {"distance": 15, "rank": 321, "pace": 342000000000, "time": 5141.5}}, "weekday": "saturday", "livingplace": "Wigoltingen"}, "sam. 15.03.2003": {"year": 2003, "day": 15, "month": 3, "categories": {"M50": {"distance": 15, "rank": 339, "pace": 374000000000, "time": 5619.2}}, "weekday": "saturday", "livingplace": "Wigoltingen"}, "sam. 20.03.2004": {"year": 2004, "day": 20, "month": 3, "categories": {"M50": {"distance": 15, "rank": 327, "pace": 366000000000, "time": 5503.2}}, "weekday": "saturday", "livingplace": "Wigoltingen"}, "sam. 17.03.2007": {"year": 2007, "day": 17, "month": 3, "categories": {"M50": {"distance": 15, "rank": 377, "pace": 355000000000, "time": 5337.3}}, "weekday": "saturday", "livingplace": "Wigoltingen"}}, "location": "Kerzers"}, "10km de Payerne": {"latitude": 46.8220266, "longitude": 6.9405663, "race": "10km de Payerne", "date": {"sam. 27.03.2010": {"year": 2010, "day": 27, "month": 3, "categories": {"M55": {"distance": 10, "rank": 13, "pace": 321000000000, "time": 3210.0}}, "weekday": "saturday", "livingplace": "Wigoltingen"}}, "location": "Payerne"}, "Rotseelauf, Ebikon": {"latitude": NaN, "longitude": NaN, "race": "Rotseelauf, Ebikon", "date": {"sam. 04.04.2009": {"year": 2009, "day": 4, "month": 4, "categories": {"M50": {"distance": 10, "rank": 111, "pace": 333000000000, "time": 3339.2}}, "weekday": "saturday", "livingplace": "smrun"}, "sam. 20.04.2013": {"year": 2013, "day": 20, "month": 4, "categories": {"10-M60": {"distance": 10, "rank": 42, "pace": 337000000000, "time": 3379.6}}, "weekday": "saturday", "livingplace": "Wigoltingen"}}, "location": "Ebikon"}, "ASICS Bremgarter Reusslauf": {"latitude": 47.34917739999999, "longitude": 8.3397905, "race": "ASICS Bremgarter Reusslauf", "date": {"sam. 23.02.2002": {"year": 2002, "day": 23, "month": 2, "categories": {"13": {"distance": 10, "rank": 440, "pace": 350000000000, "time": 3504.5}}, "weekday": "saturday", "livingplace": "Wigoltingen"}, "sam. 25.02.2006": {"year": 2006, "day": 25, "month": 2, "categories": {"M50": {"distance": 11, "rank": 265, "pace": 323000000000, "time": 3393.6}}, "weekday": "saturday", "livingplace": "Wigoltingen"}, "sam. 27.02.2010": {"year": 2010, "day": 27, "month": 2, "categories": {"M50": {"distance": 11, "rank": 340, "pace": 318000000000, "time": 3507.5}}, "weekday": "saturday", "livingplace": "smrun"}, "sam. 26.02.2011": {"year": 2011, "day": 26, "month": 2, "categories": {"M50": {"distance": 11, "rank": 326, "pace": 311000000000, "time": 3421.7}}, "weekday": "saturday", "livingplace": "smrun"}, "sam. 23.02.2008": {"year": 2008, "day": 23, "month": 2, "categories": {"M50": {"distance": 11, "rank": 338, "pace": 325000000000, "time": 3585.0}}, "weekday": "saturday", "livingplace": "smrun"}, "sam. 25.02.2012": {"year": 2012, "day": 25, "month": 2, "categories": {"M50": {"distance": 11, "rank": 394, "pace": 329000000000, "time": 3625.7}}, "weekday": "saturday", "livingplace": "smrun"}, "sam. 22.02.2014": {"year": 2014, "day": 22, "month": 2, "categories": {"11-M60": {"distance": 11, "rank": 149, "pace": 336000000000, "time": 3697.7}}, "weekday": "saturday", "livingplace": "smrun"}, "sam. 23.02.2013": {"year": 2013, "day": 23, "month": 2, "categories": {"11-M60": {"distance": 11, "rank": 128, "pace": 325000000000, "time": 3578.5}}, "weekday": "saturday", "livingplace": "smrun"}}, "location": "Bremgarten AG"}, "Bischofszeller St\u00e4dtlilauf, Bischofszell": {"latitude": NaN, "longitude": NaN, "race": "Bischofszeller St\u00e4dtlilauf, Bischofszell", "date": {"sam. 02.05.2009": {"year": 2009, "day": 2, "month": 5, "categories": {"M50": {"distance": 7, "rank": 5, "pace": 311000000000, "time": 2023.6}}, "weekday": "saturday", "livingplace": "Run Fit Thurgau"}}, "location": "Bischofszell"}, "Badener Limmat-Lauf, Baden": {"latitude": 48.5699281, "longitude": 8.5303972, "race": "Badener Limmat-Lauf, Baden", "date": {"sam. 29.03.2014": {"year": 2014, "day": 29, "month": 3, "categories": {"M60": {"distance": 13, "rank": 44, "pace": 340000000000, "time": 4487.9}}, "weekday": "saturday", "livingplace": "Wigoltingen"}, "sam. 24.03.2012": {"year": 2012, "day": 24, "month": 3, "categories": {"M50": {"distance": 13, "rank": 132, "pace": 332000000000, "time": 4376.0}}, "weekday": "saturday", "livingplace": "Wigoltingen"}, "sam. 23.03.2002": {"year": 2002, "day": 23, "month": 3, "categories": {"13": {"distance": 13, "rank": 160, "pace": 341000000000, "time": 4496.6}}, "weekday": "saturday", "livingplace": "Wigoltingen"}}, "location": "Baden"}, "Winterthur Marathon": {"latitude": 39.8088766, "longitude": -75.6037351, "race": "Winterthur Marathon", "date": {"dim. 26.05.2002": {"year": 2002, "day": 26, "month": 5, "categories": {"HM45": {"distance": 21, "rank": 51, "pace": 339000000000, "time": 7126.3}}, "weekday": "sunday", "livingplace": "Wigoltingen"}, "dim. 25.05.2003": {"year": 2003, "day": 25, "month": 5, "categories": {"HM50": {"distance": 21, "rank": 62, "pace": 337000000000, "time": 7094.1}}, "weekday": "sunday", "livingplace": "Wigoltingen"}, "dim. 18.05.2008": {"year": 2008, "day": 18, "month": 5, "categories": {"HM55": {"distance": 21, "rank": 48, "pace": 343000000000, "time": 7250.7}}, "weekday": "sunday", "livingplace": "Wigoltingen"}}, "location": "Winterthur"}, "Int Greifenseelauf, Uster": {"latitude": 47.3482747, "longitude": 8.717873899999999, "race": "Int Greifenseelauf, Uster", "date": {"sam. 17.09.2005": {"year": 2005, "day": 17, "month": 9, "categories": {"K/M50": {"distance": 6, "rank": 38, "pace": 338000000000, "time": 2100.1}}, "weekday": "saturday", "livingplace": "Wigoltingen"}, "sam. 18.09.2004": {"year": 2004, "day": 18, "month": 9, "categories": {"H/M50": {"distance": 21, "rank": 498, "pace": 389000000000, "time": 8215.7}}, "weekday": "saturday", "livingplace": "Wigoltingen"}}, "location": "Uster"}, "Pfingstlauf Wohlen AG": {"latitude": 47.3493653, "longitude": 8.2768762, "race": "Pfingstlauf Wohlen AG", "date": {"sam. 30.05.2009": {"year": 2009, "day": 30, "month": 5, "categories": {"WL-M50": {"distance": 10, "rank": 27, "pace": 353000000000, "time": 3533.8}}, "weekday": "saturday", "livingplace": "Run Fit Thurgau"}, "sam. 29.05.2004": {"year": 2004, "day": 29, "month": 5, "categories": {"WM50": {"distance": 8, "rank": 11, "pace": 367000000000, "time": 3011.4}}, "weekday": "saturday", "livingplace": "Wigoltingen"}, "sam. 18.05.2013": {"year": 2013, "day": 18, "month": 5, "categories": {"WL-M60": {"distance": 10, "rank": 14, "pace": 368000000000, "time": 3685.9}}, "weekday": "saturday", "livingplace": "Wigoltingen"}, "sam. 26.05.2012": {"year": 2012, "day": 26, "month": 5, "categories": {"WL-M50": {"distance": 10, "rank": 19, "pace": 361000000000, "time": 3616.2}}, "weekday": "saturday", "livingplace": "Wigoltingen"}, "sam. 18.05.2002": {"year": 2002, "day": 18, "month": 5, "categories": {"29": {"distance": 3, "rank": 13, "pace": 298000000000, "time": 953.7}}, "weekday": "saturday", "livingplace": "Wigoltingen"}, "sam. 07.06.2014": {"year": 2014, "day": 7, "month": 6, "categories": {"WL-M60": {"distance": 10, "rank": 14, "pace": 376000000000, "time": 3765.1}}, "weekday": "saturday", "livingplace": "Wigoltingen"}, "sam. 22.05.2010": {"year": 2010, "day": 22, "month": 5, "categories": {"WL-M50": {"distance": 10, "rank": 29, "pace": 355000000000, "time": 3555.8}}, "weekday": "saturday", "livingplace": "Wigoltingen"}, "sam. 11.06.2011": {"year": 2011, "day": 11, "month": 6, "categories": {"WL-M50": {"distance": 10, "rank": 23, "pace": 338000000000, "time": 3385.0}}, "weekday": "saturday", "livingplace": "Wigoltingen"}}, "location": "Wohlen AG"}, "Gossauer Weihnachtslauf": {"latitude": 47.4155608, "longitude": 9.248852, "race": "Gossauer Weihnachtslauf", "date": {"sam. 02.12.2006": {"year": 2006, "day": 2, "month": 12, "categories": {"27": {"distance": 6, "rank": 41, "pace": 296000000000, "time": 1831.4}}, "weekday": "saturday", "livingplace": "Wigoltingen"}}, "location": "Gossau SG"}, "Schlosslauf Rapperswil-Jona": {"latitude": 47.2266239, "longitude": 8.818437399999999, "race": "Schlosslauf Rapperswil-Jona", "date": {"dim. 07.10.2012": {"year": 2012, "day": 7, "month": 10, "categories": {"9-M4": {"distance": 9, "rank": 19, "pace": 315000000000, "time": 2849.4}}, "weekday": "sunday", "livingplace": "Run Fit Thurgau"}}, "location": "Rapperswil SG"}, "Frauenfelder": {"latitude": NaN, "longitude": NaN, "race": "Frauenfelder", "date": {"dim. 18.11.2007": {"year": 2007, "day": 18, "month": 11, "categories": {"M50": {"distance": 42, "rank": 45, "pace": 419000000000, "time": 17694.3}}, "weekday": "sunday", "livingplace": "Run Fit Thurgau"}}, "location": "Frauenfeld"}, "Sempacherseelauf, Sursee": {"latitude": NaN, "longitude": NaN, "race": "Sempacherseelauf, Sursee", "date": {"sam. 21.05.2011": {"year": 2011, "day": 21, "month": 5, "categories": {"21M50": {"distance": 21, "rank": 119, "pace": 369000000000, "time": 7789.2}}, "weekday": "saturday", "livingplace": "Wigoltingen"}}, "location": "Sursee"}, "GP Fricktal, Eiken": {"latitude": NaN, "longitude": NaN, "race": "GP Fricktal, Eiken", "date": {"sam. 23.04.2011": {"year": 2011, "day": 23, "month": 4, "categories": {"M50": {"distance": 16, "rank": 113, "pace": 332000000000, "time": 5344.1}}, "weekday": "saturday", "livingplace": "Wigoltingen"}, "sam. 07.04.2012": {"year": 2012, "day": 7, "month": 4, "categories": {"M50": {"distance": 16, "rank": 128, "pace": 328000000000, "time": 5289.8}}, "weekday": "saturday", "livingplace": "Wigoltingen"}, "sam. 11.04.2009": {"year": 2009, "day": 11, "month": 4, "categories": {"M50": {"distance": 16, "rank": 131, "pace": 351000000000, "time": 5658.0}}, "weekday": "saturday", "livingplace": "Wigoltingen"}, "sam. 03.04.2010": {"year": 2010, "day": 3, "month": 4, "categories": {"M50": {"distance": 16, "rank": 135, "pace": 327000000000, "time": 5278.2}}, "weekday": "saturday", "livingplace": "Wigoltingen"}, "sam. 07.04.2007": {"year": 2007, "day": 7, "month": 4, "categories": {"M50": {"distance": 16, "rank": 149, "pace": 368000000000, "time": 5929.1}}, "weekday": "saturday", "livingplace": "Wigoltingen"}, "sam. 22.03.2008": {"year": 2008, "day": 22, "month": 3, "categories": {"M50": {"distance": 16, "rank": 125, "pace": 320000000000, "time": 5159.7}}, "weekday": "saturday", "livingplace": "Wigoltingen"}, "sam. 30.03.2013": {"year": 2013, "day": 30, "month": 3, "categories": {"M60": {"distance": 16, "rank": 55, "pace": 347000000000, "time": 5590.6}}, "weekday": "saturday", "livingplace": "Wigoltingen"}, "sam. 30.03.2002": {"year": 2002, "day": 30, "month": 3, "categories": {"13": {"distance": 16, "rank": 215, "pace": 348000000000, "time": 5601.8}}, "weekday": "saturday", "livingplace": "Wigoltingen"}}, "location": "Eiken"}}, "birth": 1953}