{"name": "Th\u00e9voz Yvan", "sex": "M", "races": {"Morat-Fribourg": {"latitude": 46.92922110000001, "longitude": 7.120184, "race": "Morat-Fribourg", "date": {"sam. 02.10.2010": {"year": 2010, "day": 2, "month": 10, "categories": {"17-M20": {"distance": 17, "rank": 1549, "pace": 344000000000, "time": 5918.3}}, "weekday": "saturday", "livingplace": "Russy"}, "dim. 07.10.2001": {"year": 2001, "day": 7, "month": 10, "categories": {"EMA": {"distance": 3, "rank": 34, "pace": 275000000000, "time": 921.7}}, "weekday": "sunday", "livingplace": "Russy"}, "dim. 06.10.2002": {"year": 2002, "day": 6, "month": 10, "categories": {"CMB": {"distance": 9, "rank": 20, "pace": 284000000000, "time": 2444.7}}, "weekday": "sunday", "livingplace": "Russy"}}, "location": "Murten"}}, "birth": 1988}