{"name": "Vogg Walter", "sex": "M", "races": {"Bieler Lauftage, Biel Bienne": {"latitude": 47.1367785, "longitude": 7.2467909, "race": "Bieler Lauftage, Biel Bienne", "date": {"ven. 13.06.2008": {"year": 2008, "day": 13, "month": 6, "categories": {"100/M40": {"distance": 100, "rank": 13, "pace": 308000000000, "time": 30890.8}}, "weekday": "friday", "livingplace": "Dinkelscherben"}, "ven. 09.06.2006": {"year": 2006, "day": 9, "month": 6, "categories": {"100/M40": {"distance": 100, "rank": 5, "pace": 305000000000, "time": 30572.7}}, "weekday": "friday", "livingplace": "Dinkelscherben"}}, "location": "Biel/Bienne"}, "Z\u00fcrich Marathon, Teamrun und Cityrun": {"latitude": 47.3768866, "longitude": 8.541694, "race": "Z\u00fcrich Marathon, Teamrun und Cityrun", "date": {"dim. 01.04.2007": {"year": 2007, "day": 1, "month": 4, "categories": {"M40": {"distance": 42, "rank": 14, "pace": 229000000000, "time": 9680.9}}, "weekday": "sunday", "livingplace": "Dinkelscherben"}, "dim. 09.04.2006": {"year": 2006, "day": 9, "month": 4, "categories": {"M40": {"distance": 42, "rank": 25, "pace": 242000000000, "time": 10233.0}}, "weekday": "sunday", "livingplace": "Dinkelscherben"}}, "location": "Z\u00fcrich"}}, "birth": 1964}