{"name": "Von Kaenel Christian", "sex": "M", "races": {"Bl\u00fcemlisalp-Lauf, Reichenbach": {"latitude": 46.6254387, "longitude": 7.6940529, "race": "Bl\u00fcemlisalp-Lauf, Reichenbach", "date": {"dim. 30.05.2010": {"year": 2010, "day": 30, "month": 5, "categories": {"M50": {"distance": 16, "rank": 44, "pace": 423000000000, "time": 6815.1}}, "weekday": "sunday", "livingplace": "Aesch"}}, "location": "Reichenbach im Kandertal"}, "Thuner Stadtlauf, Thun": {"latitude": 46.7579868, "longitude": 7.6279881, "race": "Thuner Stadtlauf, Thun", "date": {"dim. 24.08.2008": {"year": 2008, "day": 24, "month": 8, "categories": {"10-M50": {"distance": 10, "rank": 52, "pace": 305000000000, "time": 3051.3}}, "weekday": "sunday", "livingplace": "Spiez"}}, "location": "Thun"}}, "birth": 1951}