{"name": "Walther Hans", "sex": "M", "races": {"Pfingstlauf Wohlen AG": {"latitude": 47.3493653, "longitude": 8.2768762, "race": "Pfingstlauf Wohlen AG", "date": {"sam. 07.06.2014": {"year": 2014, "day": 7, "month": 6, "categories": {"WL-M40": {"distance": 10, "rank": 11, "pace": 330000000000, "time": 3300.9}}, "weekday": "saturday", "livingplace": "Schwanden i. E."}, "sam. 18.05.2013": {"year": 2013, "day": 18, "month": 5, "categories": {"WL-M40": {"distance": 10, "rank": 19, "pace": 320000000000, "time": 3203.8}}, "weekday": "saturday", "livingplace": "Schwanden i. E."}, "sam. 11.06.2011": {"year": 2011, "day": 11, "month": 6, "categories": {"WL-M20": {"distance": 10, "rank": 15, "pace": 326000000000, "time": 3268.3}}, "weekday": "saturday", "livingplace": "Schwanden im Emmental"}}, "location": "Wohlen AG"}, "Kerzerslauf": {"latitude": 46.97488999999999, "longitude": 7.1954365, "race": "Kerzerslauf", "date": {"sam. 20.03.2010": {"year": 2010, "day": 20, "month": 3, "categories": {"15-M35": {"distance": 15, "rank": 277, "pace": 298000000000, "time": 4472.0}}, "weekday": "saturday", "livingplace": "Schwanden"}, "sam. 15.03.2003": {"year": 2003, "day": 15, "month": 3, "categories": {"M20": {"distance": 15, "rank": 415, "pace": 298000000000, "time": 4473.2}}, "weekday": "saturday", "livingplace": "Schwanden i. E."}}, "location": "Kerzers"}, "B\u00fcndner Fr\u00fchlingslauf, Domat   Ems": {"latitude": NaN, "longitude": NaN, "race": "B\u00fcndner Fr\u00fchlingslauf, Domat   Ems", "date": {"sam. 25.04.2009": {"year": 2009, "day": 25, "month": 4, "categories": {"M30": {"distance": 25, "rank": 55, "pace": 317000000000, "time": 7947.1}}, "weekday": "saturday", "livingplace": "Schwyz"}}, "location": "Thusis"}, "Lenzburger Lauf": {"latitude": 47.3904443, "longitude": 8.172154500000001, "race": "Lenzburger Lauf", "date": {"sam. 12.05.2012": {"year": 2012, "day": 12, "month": 5, "categories": {"W-M30": {"distance": 14, "rank": 6, "pace": 349000000000, "time": 5026.0}}, "weekday": "saturday", "livingplace": "Schwyz"}}, "location": "Lenzburg"}}, "birth": 1973}